{
  "last_updated": "2025-11-08T19:48:08.104861",
  "team_stats": {
    "Atlanta Hawks": {
      "games_played": 9,
      "wins": 4,
      "losses": 5,
      "win_pct": 0.444,
      "pts_scored": 114.4,
      "pts_allowed": null,
      "plus_minus": -2.0
    },
    "Boston Celtics": {
      "games_played": 10,
      "wins": 4,
      "losses": 6,
      "win_pct": 0.4,
      "pts_scored": 113.0,
      "pts_allowed": null,
      "plus_minus": 2.3
    },
    "Brooklyn Nets": {
      "games_played": 9,
      "wins": 1,
      "losses": 8,
      "win_pct": 0.111,
      "pts_scored": 111.3,
      "pts_allowed": null,
      "plus_minus": -13.2
    },
    "Charlotte Hornets": {
      "games_played": 9,
      "wins": 3,
      "losses": 6,
      "win_pct": 0.333,
      "pts_scored": 119.0,
      "pts_allowed": null,
      "plus_minus": -2.0
    },
    "Chicago Bulls": {
      "games_played": 8,
      "wins": 6,
      "losses": 2,
      "win_pct": 0.75,
      "pts_scored": 119.1,
      "pts_allowed": null,
      "plus_minus": 2.3
    },
    "Cleveland Cavaliers": {
      "games_played": 9,
      "wins": 6,
      "losses": 3,
      "win_pct": 0.667,
      "pts_scored": 119.9,
      "pts_allowed": null,
      "plus_minus": 5.1
    },
    "Dallas Mavericks": {
      "games_played": 9,
      "wins": 2,
      "losses": 7,
      "win_pct": 0.222,
      "pts_scored": 106.0,
      "pts_allowed": null,
      "plus_minus": -8.2
    },
    "Denver Nuggets": {
      "games_played": 8,
      "wins": 6,
      "losses": 2,
      "win_pct": 0.75,
      "pts_scored": 125.1,
      "pts_allowed": null,
      "plus_minus": 12.8
    },
    "Detroit Pistons": {
      "games_played": 9,
      "wins": 7,
      "losses": 2,
      "win_pct": 0.778,
      "pts_scored": 116.7,
      "pts_allowed": null,
      "plus_minus": 5.9
    },
    "Golden State Warriors": {
      "games_played": 10,
      "wins": 5,
      "losses": 5,
      "win_pct": 0.5,
      "pts_scored": 116.1,
      "pts_allowed": null,
      "plus_minus": -0.6
    },
    "Houston Rockets": {
      "games_played": 8,
      "wins": 5,
      "losses": 3,
      "win_pct": 0.625,
      "pts_scored": 122.9,
      "pts_allowed": null,
      "plus_minus": 10.0
    },
    "Indiana Pacers": {
      "games_played": 8,
      "wins": 1,
      "losses": 7,
      "win_pct": 0.125,
      "pts_scored": 111.6,
      "pts_allowed": null,
      "plus_minus": -7.9
    },
    "LA Clippers": {
      "games_played": 8,
      "wins": 3,
      "losses": 5,
      "win_pct": 0.375,
      "pts_scored": 110.5,
      "pts_allowed": null,
      "plus_minus": -4.6
    },
    "Los Angeles Lakers": {
      "games_played": 9,
      "wins": 7,
      "losses": 2,
      "win_pct": 0.778,
      "pts_scored": 119.6,
      "pts_allowed": null,
      "plus_minus": 3.0
    },
    "Memphis Grizzlies": {
      "games_played": 10,
      "wins": 4,
      "losses": 6,
      "win_pct": 0.4,
      "pts_scored": 115.1,
      "pts_allowed": null,
      "plus_minus": -4.0
    },
    "Miami Heat": {
      "games_played": 9,
      "wins": 5,
      "losses": 4,
      "win_pct": 0.556,
      "pts_scored": 122.8,
      "pts_allowed": null,
      "plus_minus": 6.2
    },
    "Milwaukee Bucks": {
      "games_played": 9,
      "wins": 6,
      "losses": 3,
      "win_pct": 0.667,
      "pts_scored": 120.6,
      "pts_allowed": null,
      "plus_minus": 2.4
    },
    "Minnesota Timberwolves": {
      "games_played": 9,
      "wins": 5,
      "losses": 4,
      "win_pct": 0.556,
      "pts_scored": 118.8,
      "pts_allowed": null,
      "plus_minus": 2.9
    },
    "New Orleans Pelicans": {
      "games_played": 8,
      "wins": 2,
      "losses": 6,
      "win_pct": 0.25,
      "pts_scored": 107.9,
      "pts_allowed": null,
      "plus_minus": -12.9
    },
    "New York Knicks": {
      "games_played": 8,
      "wins": 5,
      "losses": 3,
      "win_pct": 0.625,
      "pts_scored": 118.9,
      "pts_allowed": null,
      "plus_minus": 5.3
    },
    "Oklahoma City Thunder": {
      "games_played": 10,
      "wins": 9,
      "losses": 1,
      "win_pct": 0.9,
      "pts_scored": 123.2,
      "pts_allowed": null,
      "plus_minus": 13.5
    },
    "Orlando Magic": {
      "games_played": 9,
      "wins": 4,
      "losses": 5,
      "win_pct": 0.444,
      "pts_scored": 117.0,
      "pts_allowed": null,
      "plus_minus": 0.2
    },
    "Philadelphia 76ers": {
      "games_played": 8,
      "wins": 5,
      "losses": 3,
      "win_pct": 0.625,
      "pts_scored": 123.3,
      "pts_allowed": null,
      "plus_minus": 4.0
    },
    "Phoenix Suns": {
      "games_played": 9,
      "wins": 4,
      "losses": 5,
      "win_pct": 0.444,
      "pts_scored": 116.7,
      "pts_allowed": null,
      "plus_minus": -1.6
    },
    "Portland Trail Blazers": {
      "games_played": 8,
      "wins": 5,
      "losses": 3,
      "win_pct": 0.625,
      "pts_scored": 120.4,
      "pts_allowed": null,
      "plus_minus": 2.6
    },
    "Sacramento Kings": {
      "games_played": 9,
      "wins": 3,
      "losses": 6,
      "win_pct": 0.333,
      "pts_scored": 115.1,
      "pts_allowed": null,
      "plus_minus": -6.6
    },
    "San Antonio Spurs": {
      "games_played": 8,
      "wins": 6,
      "losses": 2,
      "win_pct": 0.75,
      "pts_scored": 118.3,
      "pts_allowed": null,
      "plus_minus": 8.6
    },
    "Toronto Raptors": {
      "games_played": 9,
      "wins": 5,
      "losses": 4,
      "win_pct": 0.556,
      "pts_scored": 119.2,
      "pts_allowed": null,
      "plus_minus": 3.6
    },
    "Utah Jazz": {
      "games_played": 9,
      "wins": 3,
      "losses": 6,
      "win_pct": 0.333,
      "pts_scored": 112.1,
      "pts_allowed": null,
      "plus_minus": -8.0
    },
    "Washington Wizards": {
      "games_played": 9,
      "wins": 1,
      "losses": 8,
      "win_pct": 0.111,
      "pts_scored": 112.2,
      "pts_allowed": null,
      "plus_minus": -18.1
    }
  },
  "friend_totals": {
    "JJ": {
      "total_wins": 24,
      "total_losses": 11,
      "total_games": 35,
      "win_pct": 0.6857142857142857,
      "point_diff_per_game": 3.775,
      "games_remaining": 293,
      "max_possible_win_pct": 0.9664634146341463,
      "teams": [
        "Thunder",
        "Spurs",
        "Pistons",
        "Pelicans"
      ],
      "is_eliminated": false
    },
    "Andy": {
      "total_wins": 20,
      "total_losses": 16,
      "total_games": 36,
      "win_pct": 0.5555555555555556,
      "point_diff_per_game": -1.9000000000000004,
      "games_remaining": 292,
      "max_possible_win_pct": 0.9512195121951219,
      "teams": [
        "Cavaliers",
        "Lakers",
        "Bucks",
        "Wizards"
      ],
      "is_eliminated": false
    },
    "Nate": {
      "total_wins": 16,
      "total_losses": 21,
      "total_games": 37,
      "win_pct": 0.43243243243243246,
      "point_diff_per_game": -1.85,
      "games_remaining": 291,
      "max_possible_win_pct": 0.9359756097560976,
      "teams": [
        "Magic",
        "Hawks",
        "Grizzlies",
        "Suns"
      ],
      "is_eliminated": false
    },
    "Chris": {
      "total_wins": 11,
      "total_losses": 25,
      "total_games": 36,
      "win_pct": 0.3055555555555556,
      "point_diff_per_game": -4.675,
      "games_remaining": 292,
      "max_possible_win_pct": 0.9237804878048781,
      "teams": [
        "Warriors",
        "Pacers",
        "Mavericks",
        "Hornets"
      ],
      "is_eliminated": false
    },
    "Adam": {
      "total_wins": 18,
      "total_losses": 18,
      "total_games": 36,
      "win_pct": 0.5,
      "point_diff_per_game": 3.6750000000000003,
      "games_remaining": 292,
      "max_possible_win_pct": 0.9451219512195121,
      "teams": [
        "Nuggets",
        "Celtics",
        "Heat",
        "Kings"
      ],
      "is_eliminated": false
    },
    "Duke": {
      "total_wins": 19,
      "total_losses": 14,
      "total_games": 33,
      "win_pct": 0.5757575757575758,
      "point_diff_per_game": 1.6500000000000001,
      "games_remaining": 295,
      "max_possible_win_pct": 0.9573170731707317,
      "teams": [
        "Knicks",
        "Clippers",
        "Raptors",
        "Bulls"
      ],
      "is_eliminated": false
    },
    "Nick": {
      "total_wins": 20,
      "total_losses": 13,
      "total_games": 33,
      "win_pct": 0.6060606060606061,
      "point_diff_per_game": 4.875,
      "games_remaining": 295,
      "max_possible_win_pct": 0.9603658536585366,
      "teams": [
        "Rockets",
        "Timberwolves",
        "76ers",
        "Trail Blazers"
      ],
      "is_eliminated": false
    },
    "Undrafted": {
      "total_wins": 4,
      "total_losses": 14,
      "total_games": 18,
      "win_pct": 0.2222222222222222,
      "point_diff_per_game": -10.6,
      "games_remaining": 146,
      "max_possible_win_pct": 0.9146341463414634,
      "teams": [
        "Nets",
        "Jazz"
      ],
      "is_eliminated": true
    }
  },
  "friend_history": {
    "JJ": [
      {
        "date": "2025-10-21",
        "win_pct": 100.0
      },
      {
        "date": "2025-10-22",
        "win_pct": 50.0
      },
      {
        "date": "2025-10-23",
        "win_pct": 60.0
      },
      {
        "date": "2025-10-24",
        "win_pct": 62.5
      },
      {
        "date": "2025-10-25",
        "win_pct": 66.66666666666666
      },
      {
        "date": "2025-10-26",
        "win_pct": 72.72727272727273
      },
      {
        "date": "2025-10-27",
        "win_pct": 66.66666666666666
      },
      {
        "date": "2025-10-28",
        "win_pct": 68.75
      },
      {
        "date": "2025-10-29",
        "win_pct": 66.66666666666666
      },
      {
        "date": "2025-10-30",
        "win_pct": 70.0
      },
      {
        "date": "2025-10-31",
        "win_pct": 66.66666666666666
      },
      {
        "date": "2025-11-01",
        "win_pct": 68.18181818181817
      },
      {
        "date": "2025-11-02",
        "win_pct": 64.0
      },
      {
        "date": "2025-11-03",
        "win_pct": 65.38461538461539
      },
      {
        "date": "2025-11-04",
        "win_pct": 67.85714285714286
      },
      {
        "date": "2025-11-05",
        "win_pct": 65.625
      },
      {
        "date": "2025-11-06",
        "win_pct": 65.625
      },
      {
        "date": "2025-11-07",
        "win_pct": 68.57142857142857
      }
    ],
    "Andy": [
      {
        "date": "2025-10-21",
        "win_pct": 18.181818181818183
      },
      {
        "date": "2025-10-22",
        "win_pct": 25.0
      },
      {
        "date": "2025-10-23",
        "win_pct": 25.0
      },
      {
        "date": "2025-10-24",
        "win_pct": 62.5
      },
      {
        "date": "2025-10-25",
        "win_pct": 62.5
      },
      {
        "date": "2025-10-26",
        "win_pct": 58.333333333333336
      },
      {
        "date": "2025-10-27",
        "win_pct": 57.14285714285714
      },
      {
        "date": "2025-10-28",
        "win_pct": 56.25
      },
      {
        "date": "2025-10-29",
        "win_pct": 55.55555555555556
      },
      {
        "date": "2025-10-30",
        "win_pct": 55.00000000000001
      },
      {
        "date": "2025-10-31",
        "win_pct": 54.54545454545454
      },
      {
        "date": "2025-11-01",
        "win_pct": 50.0
      },
      {
        "date": "2025-11-02",
        "win_pct": 53.84615384615385
      },
      {
        "date": "2025-11-03",
        "win_pct": 55.172413793103445
      },
      {
        "date": "2025-11-04",
        "win_pct": 53.333333333333336
      },
      {
        "date": "2025-11-05",
        "win_pct": 54.54545454545454
      },
      {
        "date": "2025-11-06",
        "win_pct": 54.54545454545454
      },
      {
        "date": "2025-11-07",
        "win_pct": 55.55555555555556
      }
    ],
    "Nate": [
      {
        "date": "2025-10-21",
        "win_pct": 11.11111111111111
      },
      {
        "date": "2025-10-22",
        "win_pct": 75.0
      },
      {
        "date": "2025-10-23",
        "win_pct": 75.0
      },
      {
        "date": "2025-10-24",
        "win_pct": 50.0
      },
      {
        "date": "2025-10-25",
        "win_pct": 41.66666666666667
      },
      {
        "date": "2025-10-26",
        "win_pct": 41.66666666666667
      },
      {
        "date": "2025-10-27",
        "win_pct": 31.25
      },
      {
        "date": "2025-10-28",
        "win_pct": 31.25
      },
      {
        "date": "2025-10-29",
        "win_pct": 35.0
      },
      {
        "date": "2025-10-30",
        "win_pct": 38.095238095238095
      },
      {
        "date": "2025-10-31",
        "win_pct": 41.66666666666667
      },
      {
        "date": "2025-11-01",
        "win_pct": 44.0
      },
      {
        "date": "2025-11-02",
        "win_pct": 42.857142857142854
      },
      {
        "date": "2025-11-03",
        "win_pct": 41.37931034482759
      },
      {
        "date": "2025-11-04",
        "win_pct": 40.625
      },
      {
        "date": "2025-11-05",
        "win_pct": 39.39393939393939
      },
      {
        "date": "2025-11-06",
        "win_pct": 41.17647058823529
      },
      {
        "date": "2025-11-07",
        "win_pct": 43.24324324324324
      }
    ],
    "Chris": [
      {
        "date": "2025-10-21",
        "win_pct": 100.0
      },
      {
        "date": "2025-10-22",
        "win_pct": 75.0
      },
      {
        "date": "2025-10-23",
        "win_pct": 60.0
      },
      {
        "date": "2025-10-24",
        "win_pct": 42.857142857142854
      },
      {
        "date": "2025-10-25",
        "win_pct": 33.33333333333333
      },
      {
        "date": "2025-10-26",
        "win_pct": 41.66666666666667
      },
      {
        "date": "2025-10-27",
        "win_pct": 42.857142857142854
      },
      {
        "date": "2025-10-28",
        "win_pct": 43.75
      },
      {
        "date": "2025-10-29",
        "win_pct": 44.44444444444444
      },
      {
        "date": "2025-10-30",
        "win_pct": 40.0
      },
      {
        "date": "2025-10-31",
        "win_pct": 38.095238095238095
      },
      {
        "date": "2025-11-01",
        "win_pct": 36.0
      },
      {
        "date": "2025-11-02",
        "win_pct": 38.46153846153847
      },
      {
        "date": "2025-11-03",
        "win_pct": 35.714285714285715
      },
      {
        "date": "2025-11-04",
        "win_pct": 36.666666666666664
      },
      {
        "date": "2025-11-05",
        "win_pct": 33.33333333333333
      },
      {
        "date": "2025-11-06",
        "win_pct": 33.33333333333333
      },
      {
        "date": "2025-11-07",
        "win_pct": 30.555555555555557
      }
    ],
    "Adam": [
      {
        "date": "2025-10-21",
        "win_pct": 33.33333333333333
      },
      {
        "date": "2025-10-22",
        "win_pct": 25.0
      },
      {
        "date": "2025-10-23",
        "win_pct": 0.0
      },
      {
        "date": "2025-10-24",
        "win_pct": 28.57142857142857
      },
      {
        "date": "2025-10-25",
        "win_pct": 37.5
      },
      {
        "date": "2025-10-26",
        "win_pct": 36.36363636363637
      },
      {
        "date": "2025-10-27",
        "win_pct": 46.15384615384615
      },
      {
        "date": "2025-10-28",
        "win_pct": 46.666666666666664
      },
      {
        "date": "2025-10-29",
        "win_pct": 50.0
      },
      {
        "date": "2025-10-30",
        "win_pct": 47.368421052631575
      },
      {
        "date": "2025-10-31",
        "win_pct": 47.61904761904761
      },
      {
        "date": "2025-11-01",
        "win_pct": 47.82608695652174
      },
      {
        "date": "2025-11-02",
        "win_pct": 45.83333333333333
      },
      {
        "date": "2025-11-03",
        "win_pct": 46.42857142857143
      },
      {
        "date": "2025-11-04",
        "win_pct": 46.42857142857143
      },
      {
        "date": "2025-11-05",
        "win_pct": 50.0
      },
      {
        "date": "2025-11-06",
        "win_pct": 50.0
      },
      {
        "date": "2025-11-07",
        "win_pct": 50.0
      }
    ],
    "Duke": [
      {
        "date": "2025-10-21",
        "win_pct": 33.33333333333333
      },
      {
        "date": "2025-10-22",
        "win_pct": 75.0
      },
      {
        "date": "2025-10-23",
        "win_pct": 75.0
      },
      {
        "date": "2025-10-24",
        "win_pct": 71.42857142857143
      },
      {
        "date": "2025-10-25",
        "win_pct": 75.0
      },
      {
        "date": "2025-10-26",
        "win_pct": 63.63636363636363
      },
      {
        "date": "2025-10-27",
        "win_pct": 61.53846153846154
      },
      {
        "date": "2025-10-28",
        "win_pct": 53.333333333333336
      },
      {
        "date": "2025-10-29",
        "win_pct": 52.94117647058824
      },
      {
        "date": "2025-10-30",
        "win_pct": 52.94117647058824
      },
      {
        "date": "2025-10-31",
        "win_pct": 57.14285714285714
      },
      {
        "date": "2025-11-01",
        "win_pct": 57.14285714285714
      },
      {
        "date": "2025-11-02",
        "win_pct": 58.333333333333336
      },
      {
        "date": "2025-11-03",
        "win_pct": 57.692307692307686
      },
      {
        "date": "2025-11-04",
        "win_pct": 58.620689655172406
      },
      {
        "date": "2025-11-05",
        "win_pct": 60.0
      },
      {
        "date": "2025-11-06",
        "win_pct": 58.06451612903226
      },
      {
        "date": "2025-11-07",
        "win_pct": 57.57575757575758
      }
    ],
    "Nick": [
      {
        "date": "2025-10-21",
        "win_pct": 0.0
      },
      {
        "date": "2025-10-22",
        "win_pct": 50.0
      },
      {
        "date": "2025-10-23",
        "win_pct": 50.0
      },
      {
        "date": "2025-10-24",
        "win_pct": 42.857142857142854
      },
      {
        "date": "2025-10-25",
        "win_pct": 50.0
      },
      {
        "date": "2025-10-26",
        "win_pct": 50.0
      },
      {
        "date": "2025-10-27",
        "win_pct": 57.14285714285714
      },
      {
        "date": "2025-10-28",
        "win_pct": 60.0
      },
      {
        "date": "2025-10-29",
        "win_pct": 61.111111111111114
      },
      {
        "date": "2025-10-30",
        "win_pct": 61.111111111111114
      },
      {
        "date": "2025-10-31",
        "win_pct": 60.0
      },
      {
        "date": "2025-11-01",
        "win_pct": 63.63636363636363
      },
      {
        "date": "2025-11-02",
        "win_pct": 65.21739130434783
      },
      {
        "date": "2025-11-03",
        "win_pct": 65.38461538461539
      },
      {
        "date": "2025-11-04",
        "win_pct": 62.96296296296296
      },
      {
        "date": "2025-11-05",
        "win_pct": 61.29032258064516
      },
      {
        "date": "2025-11-06",
        "win_pct": 61.29032258064516
      },
      {
        "date": "2025-11-07",
        "win_pct": 60.60606060606061
      }
    ],
    "Undrafted": [
      {
        "date": "2025-10-21",
        "win_pct": 62.5
      },
      {
        "date": "2025-10-22",
        "win_pct": 100.0
      },
      {
        "date": "2025-10-23",
        "win_pct": 100.0
      },
      {
        "date": "2025-10-24",
        "win_pct": 66.66666666666666
      },
      {
        "date": "2025-10-25",
        "win_pct": 50.0
      },
      {
        "date": "2025-10-26",
        "win_pct": 60.0
      },
      {
        "date": "2025-10-27",
        "win_pct": 66.66666666666666
      },
      {
        "date": "2025-10-28",
        "win_pct": 57.14285714285714
      },
      {
        "date": "2025-10-29",
        "win_pct": 50.0
      },
      {
        "date": "2025-10-30",
        "win_pct": 44.44444444444444
      },
      {
        "date": "2025-10-31",
        "win_pct": 40.0
      },
      {
        "date": "2025-11-01",
        "win_pct": 36.36363636363637
      },
      {
        "date": "2025-11-02",
        "win_pct": 38.46153846153847
      },
      {
        "date": "2025-11-03",
        "win_pct": 42.857142857142854
      },
      {
        "date": "2025-11-04",
        "win_pct": 40.0
      },
      {
        "date": "2025-11-05",
        "win_pct": 37.5
      },
      {
        "date": "2025-11-06",
        "win_pct": 37.5
      },
      {
        "date": "2025-11-07",
        "win_pct": 33.33333333333333
      }
    ]
  }
}