{
  "last_updated": "2026-01-23T14:00:34.682423",
  "team_stats": {
    "Atlanta Hawks": {
      "games_played": 46,
      "wins": 21,
      "losses": 25,
      "win_pct": 0.457,
      "total_pts_scored": 5410.0,
      "total_plus_minus": -67.0,
      "total_pts_allowed": 5477.0
    },
    "Austin Spurs": {
      "games_played": 11,
      "wins": 7,
      "losses": 4,
      "win_pct": 0.636,
      "total_pts_scored": 1233.0,
      "total_plus_minus": 20.0,
      "total_pts_allowed": 1213.0
    },
    "Birmingham Squadron": {
      "games_played": 16,
      "wins": 4,
      "losses": 12,
      "win_pct": 0.25,
      "total_pts_scored": 1655.0,
      "total_plus_minus": -167.0,
      "total_pts_allowed": 1822.0
    },
    "Boston Celtics": {
      "games_played": 43,
      "wins": 27,
      "losses": 16,
      "win_pct": 0.628,
      "total_pts_scored": 5021.0,
      "total_plus_minus": 298.0,
      "total_pts_allowed": 4723.0
    },
    "Brooklyn Nets": {
      "games_played": 42,
      "wins": 12,
      "losses": 30,
      "win_pct": 0.286,
      "total_pts_scored": 4533.0,
      "total_plus_minus": -274.0,
      "total_pts_allowed": 4807.0
    },
    "Capital City Go-Go": {
      "games_played": 12,
      "wins": 7,
      "losses": 5,
      "win_pct": 0.583,
      "total_pts_scored": 1346.0,
      "total_plus_minus": 102.0,
      "total_pts_allowed": 1244.0
    },
    "Charlotte Hornets": {
      "games_played": 45,
      "wins": 17,
      "losses": 28,
      "win_pct": 0.378,
      "total_pts_scored": 5217.0,
      "total_plus_minus": 20.0,
      "total_pts_allowed": 5197.0
    },
    "Chicago Bulls": {
      "games_played": 44,
      "wins": 22,
      "losses": 22,
      "win_pct": 0.5,
      "total_pts_scored": 5190.0,
      "total_plus_minus": -86.0,
      "total_pts_allowed": 5276.0
    },
    "Ciudad de Mexico Capitanes": {
      "games_played": 15,
      "wins": 12,
      "losses": 3,
      "win_pct": 0.8,
      "total_pts_scored": 1754.0,
      "total_plus_minus": 118.0,
      "total_pts_allowed": 1636.0
    },
    "Cleveland Cavaliers": {
      "games_played": 45,
      "wins": 25,
      "losses": 20,
      "win_pct": 0.556,
      "total_pts_scored": 5358.0,
      "total_plus_minus": 87.0,
      "total_pts_allowed": 5271.0
    },
    "Cleveland Charge": {
      "games_played": 11,
      "wins": 7,
      "losses": 4,
      "win_pct": 0.636,
      "total_pts_scored": 1333.0,
      "total_plus_minus": 51.0,
      "total_pts_allowed": 1282.0
    },
    "College Park Skyhawks": {
      "games_played": 14,
      "wins": 4,
      "losses": 10,
      "win_pct": 0.286,
      "total_pts_scored": 1633.0,
      "total_plus_minus": -53.0,
      "total_pts_allowed": 1686.0
    },
    "Dallas Mavericks": {
      "games_played": 45,
      "wins": 19,
      "losses": 26,
      "win_pct": 0.422,
      "total_pts_scored": 5147.0,
      "total_plus_minus": -98.0,
      "total_pts_allowed": 5245.0
    },
    "Delaware Blue Coats": {
      "games_played": 13,
      "wins": 6,
      "losses": 7,
      "win_pct": 0.462,
      "total_pts_scored": 1582.0,
      "total_plus_minus": -44.0,
      "total_pts_allowed": 1626.0
    },
    "Denver Nuggets": {
      "games_played": 45,
      "wins": 30,
      "losses": 15,
      "win_pct": 0.667,
      "total_pts_scored": 5448.0,
      "total_plus_minus": 204.0,
      "total_pts_allowed": 5244.0
    },
    "Detroit Pistons": {
      "games_played": 42,
      "wins": 32,
      "losses": 10,
      "win_pct": 0.762,
      "total_pts_scored": 4923.0,
      "total_plus_minus": 306.0,
      "total_pts_allowed": 4617.0
    },
    "Golden State Warriors": {
      "games_played": 46,
      "wins": 25,
      "losses": 21,
      "win_pct": 0.543,
      "total_pts_scored": 5375.0,
      "total_plus_minus": 124.0,
      "total_pts_allowed": 5251.0
    },
    "Grand Rapids Gold": {
      "games_played": 14,
      "wins": 5,
      "losses": 9,
      "win_pct": 0.357,
      "total_pts_scored": 1628.0,
      "total_plus_minus": -74.0,
      "total_pts_allowed": 1702.0
    },
    "Greensboro Swarm": {
      "games_played": 12,
      "wins": 9,
      "losses": 3,
      "win_pct": 0.75,
      "total_pts_scored": 1504.0,
      "total_plus_minus": 95.0,
      "total_pts_allowed": 1409.0
    },
    "Houston Rockets": {
      "games_played": 42,
      "wins": 26,
      "losses": 16,
      "win_pct": 0.619,
      "total_pts_scored": 4917.0,
      "total_plus_minus": 257.0,
      "total_pts_allowed": 4660.0
    },
    "Indiana Pacers": {
      "games_played": 45,
      "wins": 10,
      "losses": 35,
      "win_pct": 0.222,
      "total_pts_scored": 4947.0,
      "total_plus_minus": -376.0,
      "total_pts_allowed": 5323.0
    },
    "Iowa Wolves": {
      "games_played": 13,
      "wins": 7,
      "losses": 6,
      "win_pct": 0.538,
      "total_pts_scored": 1565.0,
      "total_plus_minus": 68.0,
      "total_pts_allowed": 1497.0
    },
    "LA Clippers": {
      "games_played": 44,
      "wins": 20,
      "losses": 24,
      "win_pct": 0.455,
      "total_pts_scored": 4943.0,
      "total_plus_minus": -53.0,
      "total_pts_allowed": 4996.0
    },
    "Long Island Nets": {
      "games_played": 13,
      "wins": 7,
      "losses": 6,
      "win_pct": 0.538,
      "total_pts_scored": 1487.0,
      "total_plus_minus": 17.0,
      "total_pts_allowed": 1470.0
    },
    "Los Angeles Lakers": {
      "games_played": 43,
      "wins": 26,
      "losses": 17,
      "win_pct": 0.605,
      "total_pts_scored": 4988.0,
      "total_plus_minus": -16.0,
      "total_pts_allowed": 5004.0
    },
    "Maine Celtics": {
      "games_played": 13,
      "wins": 8,
      "losses": 5,
      "win_pct": 0.615,
      "total_pts_scored": 1418.0,
      "total_plus_minus": -33.0,
      "total_pts_allowed": 1451.0
    },
    "Memphis Grizzlies": {
      "games_played": 42,
      "wins": 18,
      "losses": 24,
      "win_pct": 0.429,
      "total_pts_scored": 4841.0,
      "total_plus_minus": -41.0,
      "total_pts_allowed": 4882.0
    },
    "Memphis Hustle": {
      "games_played": 12,
      "wins": 2,
      "losses": 10,
      "win_pct": 0.167,
      "total_pts_scored": 1342.0,
      "total_plus_minus": -83.0,
      "total_pts_allowed": 1425.0
    },
    "Miami Heat": {
      "games_played": 45,
      "wins": 23,
      "losses": 22,
      "win_pct": 0.511,
      "total_pts_scored": 5370.0,
      "total_plus_minus": 40.0,
      "total_pts_allowed": 5330.0
    },
    "Milwaukee Bucks": {
      "games_played": 43,
      "wins": 18,
      "losses": 25,
      "win_pct": 0.419,
      "total_pts_scored": 4823.0,
      "total_plus_minus": -155.0,
      "total_pts_allowed": 4978.0
    },
    "Minnesota Timberwolves": {
      "games_played": 45,
      "wins": 27,
      "losses": 18,
      "win_pct": 0.6,
      "total_pts_scored": 5399.0,
      "total_plus_minus": 219.0,
      "total_pts_allowed": 5180.0
    },
    "Motor City Cruise": {
      "games_played": 13,
      "wins": 6,
      "losses": 7,
      "win_pct": 0.462,
      "total_pts_scored": 1492.0,
      "total_plus_minus": 16.0,
      "total_pts_allowed": 1476.0
    },
    "New Orleans Pelicans": {
      "games_played": 46,
      "wins": 10,
      "losses": 36,
      "win_pct": 0.217,
      "total_pts_scored": 5275.0,
      "total_plus_minus": -337.0,
      "total_pts_allowed": 5612.0
    },
    "New York Knicks": {
      "games_played": 44,
      "wins": 26,
      "losses": 18,
      "win_pct": 0.591,
      "total_pts_scored": 5189.0,
      "total_plus_minus": 183.0,
      "total_pts_allowed": 5006.0
    },
    "Noblesville Boom": {
      "games_played": 13,
      "wins": 7,
      "losses": 6,
      "win_pct": 0.538,
      "total_pts_scored": 1457.0,
      "total_plus_minus": 3.0,
      "total_pts_allowed": 1454.0
    },
    "Oklahoma City Blue": {
      "games_played": 13,
      "wins": 2,
      "losses": 11,
      "win_pct": 0.154,
      "total_pts_scored": 1323.0,
      "total_plus_minus": -216.0,
      "total_pts_allowed": 1539.0
    },
    "Oklahoma City Thunder": {
      "games_played": 45,
      "wins": 37,
      "losses": 8,
      "win_pct": 0.822,
      "total_pts_scored": 5464.0,
      "total_plus_minus": 612.0,
      "total_pts_allowed": 4852.0
    },
    "Orlando Magic": {
      "games_played": 43,
      "wins": 23,
      "losses": 20,
      "win_pct": 0.535,
      "total_pts_scored": 4973.0,
      "total_plus_minus": 12.0,
      "total_pts_allowed": 4961.0
    },
    "Osceola Magic": {
      "games_played": 11,
      "wins": 8,
      "losses": 3,
      "win_pct": 0.727,
      "total_pts_scored": 1302.0,
      "total_plus_minus": 82.0,
      "total_pts_allowed": 1220.0
    },
    "Philadelphia 76ers": {
      "games_played": 43,
      "wins": 24,
      "losses": 19,
      "win_pct": 0.558,
      "total_pts_scored": 5023.0,
      "total_plus_minus": 55.0,
      "total_pts_allowed": 4968.0
    },
    "Phoenix Suns": {
      "games_played": 44,
      "wins": 27,
      "losses": 17,
      "win_pct": 0.614,
      "total_pts_scored": 5046.0,
      "total_plus_minus": 126.0,
      "total_pts_allowed": 4920.0
    },
    "Portland Trail Blazers": {
      "games_played": 45,
      "wins": 23,
      "losses": 22,
      "win_pct": 0.511,
      "total_pts_scored": 5242.0,
      "total_plus_minus": -68.0,
      "total_pts_allowed": 5310.0
    },
    "Raptors 905": {
      "games_played": 12,
      "wins": 10,
      "losses": 2,
      "win_pct": 0.833,
      "total_pts_scored": 1347.0,
      "total_plus_minus": 173.0,
      "total_pts_allowed": 1174.0
    },
    "Rio Grande Valley Vipers": {
      "games_played": 13,
      "wins": 8,
      "losses": 5,
      "win_pct": 0.615,
      "total_pts_scored": 1518.0,
      "total_plus_minus": 6.0,
      "total_pts_allowed": 1512.0
    },
    "Rip City Remix": {
      "games_played": 14,
      "wins": 8,
      "losses": 6,
      "win_pct": 0.571,
      "total_pts_scored": 1663.0,
      "total_plus_minus": 27.0,
      "total_pts_allowed": 1636.0
    },
    "Sacramento Kings": {
      "games_played": 45,
      "wins": 12,
      "losses": 33,
      "win_pct": 0.267,
      "total_pts_scored": 4982.0,
      "total_plus_minus": -451.0,
      "total_pts_allowed": 5433.0
    },
    "Salt Lake City Stars": {
      "games_played": 13,
      "wins": 5,
      "losses": 8,
      "win_pct": 0.385,
      "total_pts_scored": 1531.0,
      "total_plus_minus": 10.0,
      "total_pts_allowed": 1521.0
    },
    "San Antonio Spurs": {
      "games_played": 45,
      "wins": 31,
      "losses": 14,
      "win_pct": 0.689,
      "total_pts_scored": 5304.0,
      "total_plus_minus": 239.0,
      "total_pts_allowed": 5065.0
    },
    "San Diego Clippers": {
      "games_played": 13,
      "wins": 5,
      "losses": 8,
      "win_pct": 0.385,
      "total_pts_scored": 1445.0,
      "total_plus_minus": -36.0,
      "total_pts_allowed": 1481.0
    },
    "Santa Cruz Warriors": {
      "games_played": 11,
      "wins": 7,
      "losses": 4,
      "win_pct": 0.636,
      "total_pts_scored": 1241.0,
      "total_plus_minus": 50.0,
      "total_pts_allowed": 1191.0
    },
    "Sioux Falls Skyforce": {
      "games_played": 13,
      "wins": 8,
      "losses": 5,
      "win_pct": 0.615,
      "total_pts_scored": 1482.0,
      "total_plus_minus": -12.0,
      "total_pts_allowed": 1494.0
    },
    "South Bay Lakers": {
      "games_played": 11,
      "wins": 5,
      "losses": 6,
      "win_pct": 0.455,
      "total_pts_scored": 1300.0,
      "total_plus_minus": 21.0,
      "total_pts_allowed": 1279.0
    },
    "Stockton Kings": {
      "games_played": 12,
      "wins": 8,
      "losses": 4,
      "win_pct": 0.667,
      "total_pts_scored": 1388.0,
      "total_plus_minus": 62.0,
      "total_pts_allowed": 1326.0
    },
    "Texas Legends": {
      "games_played": 12,
      "wins": 5,
      "losses": 7,
      "win_pct": 0.417,
      "total_pts_scored": 1391.0,
      "total_plus_minus": -38.0,
      "total_pts_allowed": 1429.0
    },
    "Toronto Raptors": {
      "games_played": 46,
      "wins": 27,
      "losses": 19,
      "win_pct": 0.587,
      "total_pts_scored": 5260.0,
      "total_plus_minus": 86.0,
      "total_pts_allowed": 5174.0
    },
    "Utah Jazz": {
      "games_played": 45,
      "wins": 15,
      "losses": 30,
      "win_pct": 0.333,
      "total_pts_scored": 5359.0,
      "total_plus_minus": -373.0,
      "total_pts_allowed": 5732.0
    },
    "Valley Suns": {
      "games_played": 12,
      "wins": 4,
      "losses": 8,
      "win_pct": 0.333,
      "total_pts_scored": 1414.0,
      "total_plus_minus": -16.0,
      "total_pts_allowed": 1430.0
    },
    "Washington Wizards": {
      "games_played": 43,
      "wins": 10,
      "losses": 33,
      "win_pct": 0.233,
      "total_pts_scored": 4824.0,
      "total_plus_minus": -473.0,
      "total_pts_allowed": 5297.0
    },
    "Westchester Knicks": {
      "games_played": 13,
      "wins": 4,
      "losses": 9,
      "win_pct": 0.308,
      "total_pts_scored": 1403.0,
      "total_plus_minus": -138.0,
      "total_pts_allowed": 1541.0
    },
    "Windy City Bulls": {
      "games_played": 10,
      "wins": 5,
      "losses": 5,
      "win_pct": 0.5,
      "total_pts_scored": 1215.0,
      "total_plus_minus": 3.0,
      "total_pts_allowed": 1212.0
    },
    "Wisconsin Herd": {
      "games_played": 14,
      "wins": 6,
      "losses": 8,
      "win_pct": 0.429,
      "total_pts_scored": 1491.0,
      "total_plus_minus": -14.0,
      "total_pts_allowed": 1505.0
    }
  },
  "friend_totals": {
    "JJ": {
      "total_wins": 110,
      "total_losses": 68,
      "total_games": 178,
      "win_pct": 0.6179775280898876,
      "point_diff_per_game": 4.606741573033708,
      "games_remaining": 150,
      "max_possible_win_pct": 0.7926829268292683,
      "teams": [
        "Oklahoma City Thunder",
        "San Antonio Spurs",
        "Detroit Pistons",
        "New Orleans Pelicans"
      ],
      "is_eliminated": false
    },
    "Andy": {
      "total_wins": 79,
      "total_losses": 95,
      "total_games": 174,
      "win_pct": 0.4540229885057471,
      "point_diff_per_game": -3.2011494252873565,
      "games_remaining": 154,
      "max_possible_win_pct": 0.7103658536585366,
      "teams": [
        "Cleveland Cavaliers",
        "Los Angeles Lakers",
        "Milwaukee Bucks",
        "Washington Wizards"
      ],
      "is_eliminated": false
    },
    "Nate": {
      "total_wins": 89,
      "total_losses": 86,
      "total_games": 175,
      "win_pct": 0.5085714285714286,
      "point_diff_per_game": 0.17142857142857143,
      "games_remaining": 153,
      "max_possible_win_pct": 0.7378048780487805,
      "teams": [
        "Orlando Magic",
        "Atlanta Hawks",
        "Memphis Grizzlies",
        "Phoenix Suns"
      ],
      "is_eliminated": false
    },
    "Chris": {
      "total_wins": 71,
      "total_losses": 110,
      "total_games": 181,
      "win_pct": 0.39226519337016574,
      "point_diff_per_game": -1.8232044198895028,
      "games_remaining": 147,
      "max_possible_win_pct": 0.6646341463414634,
      "teams": [
        "Golden State Warriors",
        "Indiana Pacers",
        "Dallas Mavericks",
        "Charlotte Hornets"
      ],
      "is_eliminated": false
    },
    "Adam": {
      "total_wins": 92,
      "total_losses": 86,
      "total_games": 178,
      "win_pct": 0.5168539325842697,
      "point_diff_per_game": 0.5112359550561798,
      "games_remaining": 150,
      "max_possible_win_pct": 0.7378048780487805,
      "teams": [
        "Denver Nuggets",
        "Boston Celtics",
        "Miami Heat",
        "Sacramento Kings"
      ],
      "is_eliminated": false
    },
    "Duke": {
      "total_wins": 95,
      "total_losses": 83,
      "total_games": 178,
      "win_pct": 0.5337078651685393,
      "point_diff_per_game": 0.7303370786516854,
      "games_remaining": 150,
      "max_possible_win_pct": 0.7469512195121951,
      "teams": [
        "New York Knicks",
        "LA Clippers",
        "Toronto Raptors",
        "Chicago Bulls"
      ],
      "is_eliminated": false
    },
    "Nick": {
      "total_wins": 100,
      "total_losses": 75,
      "total_games": 175,
      "win_pct": 0.5714285714285714,
      "point_diff_per_game": 2.645714285714286,
      "games_remaining": 153,
      "max_possible_win_pct": 0.7713414634146342,
      "teams": [
        "Houston Rockets",
        "Minnesota Timberwolves",
        "Philadelphia 76ers",
        "Portland Trail Blazers"
      ],
      "is_eliminated": false
    },
    "Undrafted": {
      "total_wins": 27,
      "total_losses": 60,
      "total_games": 87,
      "win_pct": 0.3103448275862069,
      "point_diff_per_game": -7.436781609195402,
      "games_remaining": 77,
      "max_possible_win_pct": 0.6341463414634146,
      "teams": [
        "Brooklyn Nets",
        "Utah Jazz"
      ],
      "is_eliminated": true
    }
  },
  "friend_history": {
    "JJ": [
      {
        "date": "2025-10-21",
        "win_pct": 100.0
      },
      {
        "date": "2025-10-22",
        "win_pct": 50.0
      },
      {
        "date": "2025-10-23",
        "win_pct": 60.0
      },
      {
        "date": "2025-10-24",
        "win_pct": 62.5
      },
      {
        "date": "2025-10-25",
        "win_pct": 66.66666666666666
      },
      {
        "date": "2025-10-26",
        "win_pct": 72.72727272727273
      },
      {
        "date": "2025-10-27",
        "win_pct": 66.66666666666666
      },
      {
        "date": "2025-10-28",
        "win_pct": 68.75
      },
      {
        "date": "2025-10-29",
        "win_pct": 66.66666666666666
      },
      {
        "date": "2025-10-30",
        "win_pct": 70.0
      },
      {
        "date": "2025-10-31",
        "win_pct": 66.66666666666666
      },
      {
        "date": "2025-11-01",
        "win_pct": 68.18181818181817
      },
      {
        "date": "2025-11-02",
        "win_pct": 64.0
      },
      {
        "date": "2025-11-03",
        "win_pct": 65.38461538461539
      },
      {
        "date": "2025-11-04",
        "win_pct": 67.85714285714286
      },
      {
        "date": "2025-11-05",
        "win_pct": 65.625
      },
      {
        "date": "2025-11-06",
        "win_pct": 65.625
      },
      {
        "date": "2025-11-07",
        "win_pct": 68.57142857142857
      },
      {
        "date": "2025-11-08",
        "win_pct": 67.56756756756756
      },
      {
        "date": "2025-11-09",
        "win_pct": 69.23076923076923
      },
      {
        "date": "2025-11-10",
        "win_pct": 69.04761904761905
      },
      {
        "date": "2025-11-11",
        "win_pct": 69.76744186046511
      },
      {
        "date": "2025-11-12",
        "win_pct": 68.08510638297872
      },
      {
        "date": "2025-11-13",
        "win_pct": 68.08510638297872
      },
      {
        "date": "2025-11-14",
        "win_pct": 66.0
      },
      {
        "date": "2025-11-15",
        "win_pct": 66.66666666666666
      },
      {
        "date": "2025-11-16",
        "win_pct": 66.0377358490566
      },
      {
        "date": "2025-11-17",
        "win_pct": 66.07142857142857
      },
      {
        "date": "2025-11-18",
        "win_pct": 67.24137931034483
      },
      {
        "date": "2025-11-19",
        "win_pct": 66.66666666666666
      },
      {
        "date": "2025-11-20",
        "win_pct": 67.21311475409836
      },
      {
        "date": "2025-11-21",
        "win_pct": 66.66666666666666
      },
      {
        "date": "2025-11-22",
        "win_pct": 66.15384615384615
      },
      {
        "date": "2025-11-23",
        "win_pct": 65.67164179104478
      },
      {
        "date": "2025-11-24",
        "win_pct": 66.66666666666666
      },
      {
        "date": "2025-11-25",
        "win_pct": 66.66666666666666
      },
      {
        "date": "2025-11-26",
        "win_pct": 65.75342465753424
      },
      {
        "date": "2025-11-28",
        "win_pct": 65.78947368421053
      },
      {
        "date": "2025-11-29",
        "win_pct": 65.38461538461539
      },
      {
        "date": "2025-11-30",
        "win_pct": 64.19753086419753
      },
      {
        "date": "2025-12-01",
        "win_pct": 64.63414634146342
      },
      {
        "date": "2025-12-02",
        "win_pct": 64.70588235294117
      },
      {
        "date": "2025-12-03",
        "win_pct": 64.36781609195403
      },
      {
        "date": "2025-12-04",
        "win_pct": 63.63636363636363
      },
      {
        "date": "2025-12-05",
        "win_pct": 63.73626373626373
      },
      {
        "date": "2025-12-06",
        "win_pct": 63.44086021505376
      },
      {
        "date": "2025-12-07",
        "win_pct": 63.829787234042556
      },
      {
        "date": "2025-12-08",
        "win_pct": 63.541666666666664
      },
      {
        "date": "2025-12-09",
        "win_pct": 63.541666666666664
      },
      {
        "date": "2025-12-10",
        "win_pct": 64.28571428571429
      },
      {
        "date": "2025-12-11",
        "win_pct": 64.64646464646465
      },
      {
        "date": "2025-12-12",
        "win_pct": 65.0
      },
      {
        "date": "2025-12-13",
        "win_pct": 64.70588235294117
      },
      {
        "date": "2025-12-14",
        "win_pct": 65.0485436893204
      },
      {
        "date": "2025-12-15",
        "win_pct": 65.38461538461539
      },
      {
        "date": "2025-12-17",
        "win_pct": 65.38461538461539
      },
      {
        "date": "2025-12-18",
        "win_pct": 65.74074074074075
      },
      {
        "date": "2025-12-19",
        "win_pct": 65.45454545454545
      },
      {
        "date": "2025-12-20",
        "win_pct": 66.07142857142857
      },
      {
        "date": "2025-12-21",
        "win_pct": 66.3716814159292
      },
      {
        "date": "2025-12-22",
        "win_pct": 67.24137931034483
      },
      {
        "date": "2025-12-23",
        "win_pct": 66.66666666666666
      },
      {
        "date": "2025-12-25",
        "win_pct": 66.39344262295081
      },
      {
        "date": "2025-12-26",
        "win_pct": 65.32258064516128
      },
      {
        "date": "2025-12-27",
        "win_pct": 64.28571428571429
      },
      {
        "date": "2025-12-28",
        "win_pct": 64.0625
      },
      {
        "date": "2025-12-29",
        "win_pct": 63.358778625954194
      },
      {
        "date": "2025-12-30",
        "win_pct": 63.63636363636363
      },
      {
        "date": "2025-12-31",
        "win_pct": 63.70370370370371
      },
      {
        "date": "2026-01-01",
        "win_pct": 63.23529411764706
      },
      {
        "date": "2026-01-02",
        "win_pct": 63.30935251798561
      },
      {
        "date": "2026-01-03",
        "win_pct": 62.857142857142854
      },
      {
        "date": "2026-01-04",
        "win_pct": 62.23776223776224
      },
      {
        "date": "2026-01-05",
        "win_pct": 62.06896551724138
      },
      {
        "date": "2026-01-06",
        "win_pct": 61.224489795918366
      },
      {
        "date": "2026-01-07",
        "win_pct": 61.58940397350994
      },
      {
        "date": "2026-01-08",
        "win_pct": 61.58940397350994
      },
      {
        "date": "2026-01-09",
        "win_pct": 62.091503267973856
      },
      {
        "date": "2026-01-10",
        "win_pct": 61.935483870967744
      },
      {
        "date": "2026-01-11",
        "win_pct": 61.39240506329114
      },
      {
        "date": "2026-01-12",
        "win_pct": 61.39240506329114
      },
      {
        "date": "2026-01-13",
        "win_pct": 60.86956521739131
      },
      {
        "date": "2026-01-14",
        "win_pct": 61.111111111111114
      },
      {
        "date": "2026-01-15",
        "win_pct": 61.81818181818181
      },
      {
        "date": "2026-01-16",
        "win_pct": 61.44578313253012
      },
      {
        "date": "2026-01-17",
        "win_pct": 61.53846153846154
      },
      {
        "date": "2026-01-18",
        "win_pct": 61.1764705882353
      },
      {
        "date": "2026-01-19",
        "win_pct": 61.849710982658955
      },
      {
        "date": "2026-01-20",
        "win_pct": 61.49425287356321
      },
      {
        "date": "2026-01-21",
        "win_pct": 61.5819209039548
      },
      {
        "date": "2026-01-22",
        "win_pct": 61.79775280898876
      }
    ],
    "Andy": [
      {
        "date": "2025-10-21",
        "win_pct": 0.0
      },
      {
        "date": "2025-10-22",
        "win_pct": 25.0
      },
      {
        "date": "2025-10-23",
        "win_pct": 25.0
      },
      {
        "date": "2025-10-24",
        "win_pct": 62.5
      },
      {
        "date": "2025-10-25",
        "win_pct": 62.5
      },
      {
        "date": "2025-10-26",
        "win_pct": 58.333333333333336
      },
      {
        "date": "2025-10-27",
        "win_pct": 57.14285714285714
      },
      {
        "date": "2025-10-28",
        "win_pct": 56.25
      },
      {
        "date": "2025-10-29",
        "win_pct": 55.55555555555556
      },
      {
        "date": "2025-10-30",
        "win_pct": 55.00000000000001
      },
      {
        "date": "2025-10-31",
        "win_pct": 54.54545454545454
      },
      {
        "date": "2025-11-01",
        "win_pct": 50.0
      },
      {
        "date": "2025-11-02",
        "win_pct": 53.84615384615385
      },
      {
        "date": "2025-11-03",
        "win_pct": 55.172413793103445
      },
      {
        "date": "2025-11-04",
        "win_pct": 53.333333333333336
      },
      {
        "date": "2025-11-05",
        "win_pct": 54.54545454545454
      },
      {
        "date": "2025-11-06",
        "win_pct": 54.54545454545454
      },
      {
        "date": "2025-11-07",
        "win_pct": 55.55555555555556
      },
      {
        "date": "2025-11-08",
        "win_pct": 53.84615384615385
      },
      {
        "date": "2025-11-09",
        "win_pct": 52.5
      },
      {
        "date": "2025-11-10",
        "win_pct": 52.27272727272727
      },
      {
        "date": "2025-11-11",
        "win_pct": 52.27272727272727
      },
      {
        "date": "2025-11-12",
        "win_pct": 50.0
      },
      {
        "date": "2025-11-13",
        "win_pct": 48.97959183673469
      },
      {
        "date": "2025-11-14",
        "win_pct": 50.98039215686274
      },
      {
        "date": "2025-11-15",
        "win_pct": 51.85185185185185
      },
      {
        "date": "2025-11-16",
        "win_pct": 50.90909090909091
      },
      {
        "date": "2025-11-17",
        "win_pct": 50.877192982456144
      },
      {
        "date": "2025-11-18",
        "win_pct": 51.724137931034484
      },
      {
        "date": "2025-11-19",
        "win_pct": 50.0
      },
      {
        "date": "2025-11-20",
        "win_pct": 49.18032786885246
      },
      {
        "date": "2025-11-21",
        "win_pct": 49.2063492063492
      },
      {
        "date": "2025-11-22",
        "win_pct": 47.69230769230769
      },
      {
        "date": "2025-11-23",
        "win_pct": 49.25373134328358
      },
      {
        "date": "2025-11-24",
        "win_pct": 47.82608695652174
      },
      {
        "date": "2025-11-25",
        "win_pct": 49.29577464788733
      },
      {
        "date": "2025-11-26",
        "win_pct": 48.61111111111111
      },
      {
        "date": "2025-11-28",
        "win_pct": 47.368421052631575
      },
      {
        "date": "2025-11-29",
        "win_pct": 48.05194805194805
      },
      {
        "date": "2025-11-30",
        "win_pct": 48.10126582278481
      },
      {
        "date": "2025-12-01",
        "win_pct": 48.19277108433735
      },
      {
        "date": "2025-12-02",
        "win_pct": 47.61904761904761
      },
      {
        "date": "2025-12-03",
        "win_pct": 47.674418604651166
      },
      {
        "date": "2025-12-04",
        "win_pct": 47.72727272727273
      },
      {
        "date": "2025-12-05",
        "win_pct": 47.25274725274725
      },
      {
        "date": "2025-12-06",
        "win_pct": 45.744680851063826
      },
      {
        "date": "2025-12-07",
        "win_pct": 46.31578947368421
      },
      {
        "date": "2025-12-08",
        "win_pct": 46.31578947368421
      },
      {
        "date": "2025-12-09",
        "win_pct": 46.31578947368421
      },
      {
        "date": "2025-12-10",
        "win_pct": 45.83333333333333
      },
      {
        "date": "2025-12-11",
        "win_pct": 46.391752577319586
      },
      {
        "date": "2025-12-12",
        "win_pct": 46.464646464646464
      },
      {
        "date": "2025-12-13",
        "win_pct": 46.464646464646464
      },
      {
        "date": "2025-12-14",
        "win_pct": 46.601941747572816
      },
      {
        "date": "2025-12-15",
        "win_pct": 46.601941747572816
      },
      {
        "date": "2025-12-17",
        "win_pct": 46.15384615384615
      },
      {
        "date": "2025-12-18",
        "win_pct": 45.794392523364486
      },
      {
        "date": "2025-12-19",
        "win_pct": 45.370370370370374
      },
      {
        "date": "2025-12-20",
        "win_pct": 45.45454545454545
      },
      {
        "date": "2025-12-21",
        "win_pct": 44.642857142857146
      },
      {
        "date": "2025-12-22",
        "win_pct": 45.13274336283185
      },
      {
        "date": "2025-12-23",
        "win_pct": 45.2991452991453
      },
      {
        "date": "2025-12-25",
        "win_pct": 44.537815126050425
      },
      {
        "date": "2025-12-26",
        "win_pct": 44.62809917355372
      },
      {
        "date": "2025-12-27",
        "win_pct": 44.71544715447154
      },
      {
        "date": "2025-12-28",
        "win_pct": 45.6
      },
      {
        "date": "2025-12-29",
        "win_pct": 46.09375
      },
      {
        "date": "2025-12-30",
        "win_pct": 45.73643410852713
      },
      {
        "date": "2025-12-31",
        "win_pct": 46.21212121212121
      },
      {
        "date": "2026-01-01",
        "win_pct": 46.21212121212121
      },
      {
        "date": "2026-01-02",
        "win_pct": 47.794117647058826
      },
      {
        "date": "2026-01-03",
        "win_pct": 47.794117647058826
      },
      {
        "date": "2026-01-04",
        "win_pct": 47.85714285714286
      },
      {
        "date": "2026-01-05",
        "win_pct": 47.85714285714286
      },
      {
        "date": "2026-01-06",
        "win_pct": 48.95104895104895
      },
      {
        "date": "2026-01-07",
        "win_pct": 47.94520547945205
      },
      {
        "date": "2026-01-08",
        "win_pct": 47.61904761904761
      },
      {
        "date": "2026-01-09",
        "win_pct": 47.333333333333336
      },
      {
        "date": "2026-01-10",
        "win_pct": 47.682119205298015
      },
      {
        "date": "2026-01-11",
        "win_pct": 47.05882352941176
      },
      {
        "date": "2026-01-12",
        "win_pct": 46.45161290322581
      },
      {
        "date": "2026-01-13",
        "win_pct": 46.496815286624205
      },
      {
        "date": "2026-01-14",
        "win_pct": 46.540880503144656
      },
      {
        "date": "2026-01-15",
        "win_pct": 45.962732919254655
      },
      {
        "date": "2026-01-16",
        "win_pct": 46.012269938650306
      },
      {
        "date": "2026-01-17",
        "win_pct": 45.45454545454545
      },
      {
        "date": "2026-01-18",
        "win_pct": 45.78313253012048
      },
      {
        "date": "2026-01-19",
        "win_pct": 45.562130177514796
      },
      {
        "date": "2026-01-20",
        "win_pct": 45.88235294117647
      },
      {
        "date": "2026-01-21",
        "win_pct": 45.93023255813954
      },
      {
        "date": "2026-01-22",
        "win_pct": 45.40229885057471
      }
    ],
    "Nate": [
      {
        "date": "2025-10-21",
        "win_pct": 0
      },
      {
        "date": "2025-10-22",
        "win_pct": 75.0
      },
      {
        "date": "2025-10-23",
        "win_pct": 75.0
      },
      {
        "date": "2025-10-24",
        "win_pct": 50.0
      },
      {
        "date": "2025-10-25",
        "win_pct": 41.66666666666667
      },
      {
        "date": "2025-10-26",
        "win_pct": 41.66666666666667
      },
      {
        "date": "2025-10-27",
        "win_pct": 31.25
      },
      {
        "date": "2025-10-28",
        "win_pct": 31.25
      },
      {
        "date": "2025-10-29",
        "win_pct": 35.0
      },
      {
        "date": "2025-10-30",
        "win_pct": 38.095238095238095
      },
      {
        "date": "2025-10-31",
        "win_pct": 41.66666666666667
      },
      {
        "date": "2025-11-01",
        "win_pct": 44.0
      },
      {
        "date": "2025-11-02",
        "win_pct": 42.857142857142854
      },
      {
        "date": "2025-11-03",
        "win_pct": 41.37931034482759
      },
      {
        "date": "2025-11-04",
        "win_pct": 40.625
      },
      {
        "date": "2025-11-05",
        "win_pct": 39.39393939393939
      },
      {
        "date": "2025-11-06",
        "win_pct": 41.17647058823529
      },
      {
        "date": "2025-11-07",
        "win_pct": 43.24324324324324
      },
      {
        "date": "2025-11-08",
        "win_pct": 46.15384615384615
      },
      {
        "date": "2025-11-09",
        "win_pct": 43.90243902439025
      },
      {
        "date": "2025-11-10",
        "win_pct": 47.72727272727273
      },
      {
        "date": "2025-11-11",
        "win_pct": 46.666666666666664
      },
      {
        "date": "2025-11-12",
        "win_pct": 48.97959183673469
      },
      {
        "date": "2025-11-13",
        "win_pct": 50.98039215686274
      },
      {
        "date": "2025-11-14",
        "win_pct": 51.92307692307693
      },
      {
        "date": "2025-11-15",
        "win_pct": 50.943396226415096
      },
      {
        "date": "2025-11-16",
        "win_pct": 50.0
      },
      {
        "date": "2025-11-17",
        "win_pct": 50.0
      },
      {
        "date": "2025-11-18",
        "win_pct": 50.0
      },
      {
        "date": "2025-11-19",
        "win_pct": 50.0
      },
      {
        "date": "2025-11-20",
        "win_pct": 50.79365079365079
      },
      {
        "date": "2025-11-21",
        "win_pct": 51.5625
      },
      {
        "date": "2025-11-22",
        "win_pct": 53.73134328358209
      },
      {
        "date": "2025-11-23",
        "win_pct": 54.285714285714285
      },
      {
        "date": "2025-11-24",
        "win_pct": 52.77777777777778
      },
      {
        "date": "2025-11-25",
        "win_pct": 52.702702702702695
      },
      {
        "date": "2025-11-26",
        "win_pct": 53.94736842105263
      },
      {
        "date": "2025-11-28",
        "win_pct": 55.00000000000001
      },
      {
        "date": "2025-11-29",
        "win_pct": 54.32098765432099
      },
      {
        "date": "2025-11-30",
        "win_pct": 55.42168674698795
      },
      {
        "date": "2025-12-01",
        "win_pct": 55.81395348837209
      },
      {
        "date": "2025-12-02",
        "win_pct": 55.172413793103445
      },
      {
        "date": "2025-12-03",
        "win_pct": 53.93258426966292
      },
      {
        "date": "2025-12-04",
        "win_pct": 53.93258426966292
      },
      {
        "date": "2025-12-05",
        "win_pct": 53.76344086021505
      },
      {
        "date": "2025-12-06",
        "win_pct": 54.25531914893617
      },
      {
        "date": "2025-12-07",
        "win_pct": 54.166666666666664
      },
      {
        "date": "2025-12-08",
        "win_pct": 54.63917525773196
      },
      {
        "date": "2025-12-09",
        "win_pct": 55.10204081632652
      },
      {
        "date": "2025-12-10",
        "win_pct": 54.54545454545454
      },
      {
        "date": "2025-12-11",
        "win_pct": 54.54545454545454
      },
      {
        "date": "2025-12-12",
        "win_pct": 53.46534653465347
      },
      {
        "date": "2025-12-13",
        "win_pct": 52.94117647058824
      },
      {
        "date": "2025-12-14",
        "win_pct": 52.88461538461539
      },
      {
        "date": "2025-12-15",
        "win_pct": 53.333333333333336
      },
      {
        "date": "2025-12-17",
        "win_pct": 53.77358490566038
      },
      {
        "date": "2025-12-18",
        "win_pct": 53.21100917431193
      },
      {
        "date": "2025-12-19",
        "win_pct": 52.72727272727272
      },
      {
        "date": "2025-12-20",
        "win_pct": 52.21238938053098
      },
      {
        "date": "2025-12-21",
        "win_pct": 51.75438596491229
      },
      {
        "date": "2025-12-22",
        "win_pct": 50.86206896551724
      },
      {
        "date": "2025-12-23",
        "win_pct": 51.66666666666667
      },
      {
        "date": "2025-12-25",
        "win_pct": 51.66666666666667
      },
      {
        "date": "2025-12-26",
        "win_pct": 51.61290322580645
      },
      {
        "date": "2025-12-27",
        "win_pct": 51.96850393700787
      },
      {
        "date": "2025-12-28",
        "win_pct": 51.5625
      },
      {
        "date": "2025-12-29",
        "win_pct": 51.14503816793893
      },
      {
        "date": "2025-12-30",
        "win_pct": 50.75757575757576
      },
      {
        "date": "2025-12-31",
        "win_pct": 51.11111111111111
      },
      {
        "date": "2026-01-01",
        "win_pct": 51.11111111111111
      },
      {
        "date": "2026-01-02",
        "win_pct": 51.07913669064749
      },
      {
        "date": "2026-01-03",
        "win_pct": 50.71428571428571
      },
      {
        "date": "2026-01-04",
        "win_pct": 51.048951048951054
      },
      {
        "date": "2026-01-05",
        "win_pct": 50.3448275862069
      },
      {
        "date": "2026-01-06",
        "win_pct": 50.34013605442177
      },
      {
        "date": "2026-01-07",
        "win_pct": 50.993377483443716
      },
      {
        "date": "2026-01-08",
        "win_pct": 50.993377483443716
      },
      {
        "date": "2026-01-09",
        "win_pct": 50.967741935483865
      },
      {
        "date": "2026-01-10",
        "win_pct": 50.967741935483865
      },
      {
        "date": "2026-01-11",
        "win_pct": 52.20125786163522
      },
      {
        "date": "2026-01-12",
        "win_pct": 52.20125786163522
      },
      {
        "date": "2026-01-13",
        "win_pct": 51.5527950310559
      },
      {
        "date": "2026-01-14",
        "win_pct": 51.5527950310559
      },
      {
        "date": "2026-01-15",
        "win_pct": 50.90909090909091
      },
      {
        "date": "2026-01-16",
        "win_pct": 50.90909090909091
      },
      {
        "date": "2026-01-17",
        "win_pct": 50.898203592814376
      },
      {
        "date": "2026-01-18",
        "win_pct": 50.887573964497044
      },
      {
        "date": "2026-01-19",
        "win_pct": 50.877192982456144
      },
      {
        "date": "2026-01-20",
        "win_pct": 51.162790697674424
      },
      {
        "date": "2026-01-21",
        "win_pct": 51.14942528735632
      },
      {
        "date": "2026-01-22",
        "win_pct": 50.857142857142854
      }
    ],
    "Chris": [
      {
        "date": "2025-10-21",
        "win_pct": 100.0
      },
      {
        "date": "2025-10-22",
        "win_pct": 66.66666666666666
      },
      {
        "date": "2025-10-23",
        "win_pct": 60.0
      },
      {
        "date": "2025-10-24",
        "win_pct": 42.857142857142854
      },
      {
        "date": "2025-10-25",
        "win_pct": 33.33333333333333
      },
      {
        "date": "2025-10-26",
        "win_pct": 41.66666666666667
      },
      {
        "date": "2025-10-27",
        "win_pct": 42.857142857142854
      },
      {
        "date": "2025-10-28",
        "win_pct": 43.75
      },
      {
        "date": "2025-10-29",
        "win_pct": 44.44444444444444
      },
      {
        "date": "2025-10-30",
        "win_pct": 40.0
      },
      {
        "date": "2025-10-31",
        "win_pct": 38.095238095238095
      },
      {
        "date": "2025-11-01",
        "win_pct": 36.0
      },
      {
        "date": "2025-11-02",
        "win_pct": 38.46153846153847
      },
      {
        "date": "2025-11-03",
        "win_pct": 35.714285714285715
      },
      {
        "date": "2025-11-04",
        "win_pct": 36.666666666666664
      },
      {
        "date": "2025-11-05",
        "win_pct": 33.33333333333333
      },
      {
        "date": "2025-11-06",
        "win_pct": 33.33333333333333
      },
      {
        "date": "2025-11-07",
        "win_pct": 30.555555555555557
      },
      {
        "date": "2025-11-08",
        "win_pct": 31.57894736842105
      },
      {
        "date": "2025-11-09",
        "win_pct": 32.5
      },
      {
        "date": "2025-11-10",
        "win_pct": 30.952380952380953
      },
      {
        "date": "2025-11-11",
        "win_pct": 29.545454545454547
      },
      {
        "date": "2025-11-12",
        "win_pct": 31.914893617021278
      },
      {
        "date": "2025-11-13",
        "win_pct": 31.25
      },
      {
        "date": "2025-11-14",
        "win_pct": 31.372549019607842
      },
      {
        "date": "2025-11-15",
        "win_pct": 30.18867924528302
      },
      {
        "date": "2025-11-16",
        "win_pct": 32.72727272727273
      },
      {
        "date": "2025-11-17",
        "win_pct": 31.03448275862069
      },
      {
        "date": "2025-11-18",
        "win_pct": 30.508474576271187
      },
      {
        "date": "2025-11-19",
        "win_pct": 30.158730158730158
      },
      {
        "date": "2025-11-20",
        "win_pct": 30.158730158730158
      },
      {
        "date": "2025-11-21",
        "win_pct": 30.303030303030305
      },
      {
        "date": "2025-11-22",
        "win_pct": 29.411764705882355
      },
      {
        "date": "2025-11-23",
        "win_pct": 28.985507246376812
      },
      {
        "date": "2025-11-24",
        "win_pct": 29.166666666666668
      },
      {
        "date": "2025-11-25",
        "win_pct": 29.166666666666668
      },
      {
        "date": "2025-11-26",
        "win_pct": 28.000000000000004
      },
      {
        "date": "2025-11-28",
        "win_pct": 29.48717948717949
      },
      {
        "date": "2025-11-29",
        "win_pct": 32.926829268292686
      },
      {
        "date": "2025-11-30",
        "win_pct": 32.926829268292686
      },
      {
        "date": "2025-12-01",
        "win_pct": 32.94117647058823
      },
      {
        "date": "2025-12-02",
        "win_pct": 32.55813953488372
      },
      {
        "date": "2025-12-03",
        "win_pct": 32.58426966292135
      },
      {
        "date": "2025-12-04",
        "win_pct": 32.22222222222222
      },
      {
        "date": "2025-12-05",
        "win_pct": 33.33333333333333
      },
      {
        "date": "2025-12-06",
        "win_pct": 34.73684210526316
      },
      {
        "date": "2025-12-07",
        "win_pct": 35.051546391752574
      },
      {
        "date": "2025-12-08",
        "win_pct": 35.714285714285715
      },
      {
        "date": "2025-12-09",
        "win_pct": 35.714285714285715
      },
      {
        "date": "2025-12-10",
        "win_pct": 35.714285714285715
      },
      {
        "date": "2025-12-11",
        "win_pct": 35.714285714285715
      },
      {
        "date": "2025-12-12",
        "win_pct": 35.294117647058826
      },
      {
        "date": "2025-12-13",
        "win_pct": 35.294117647058826
      },
      {
        "date": "2025-12-14",
        "win_pct": 35.23809523809524
      },
      {
        "date": "2025-12-15",
        "win_pct": 34.90566037735849
      },
      {
        "date": "2025-12-17",
        "win_pct": 34.90566037735849
      },
      {
        "date": "2025-12-18",
        "win_pct": 35.45454545454545
      },
      {
        "date": "2025-12-19",
        "win_pct": 35.45454545454545
      },
      {
        "date": "2025-12-20",
        "win_pct": 35.08771929824561
      },
      {
        "date": "2025-12-21",
        "win_pct": 35.08771929824561
      },
      {
        "date": "2025-12-22",
        "win_pct": 34.74576271186441
      },
      {
        "date": "2025-12-23",
        "win_pct": 35.53719008264463
      },
      {
        "date": "2025-12-25",
        "win_pct": 35.77235772357724
      },
      {
        "date": "2025-12-26",
        "win_pct": 36.0
      },
      {
        "date": "2025-12-27",
        "win_pct": 35.43307086614173
      },
      {
        "date": "2025-12-28",
        "win_pct": 35.15625
      },
      {
        "date": "2025-12-29",
        "win_pct": 34.84848484848485
      },
      {
        "date": "2025-12-30",
        "win_pct": 34.84848484848485
      },
      {
        "date": "2025-12-31",
        "win_pct": 34.81481481481482
      },
      {
        "date": "2026-01-01",
        "win_pct": 34.55882352941176
      },
      {
        "date": "2026-01-02",
        "win_pct": 33.81294964028777
      },
      {
        "date": "2026-01-03",
        "win_pct": 35.2112676056338
      },
      {
        "date": "2026-01-04",
        "win_pct": 34.96503496503497
      },
      {
        "date": "2026-01-05",
        "win_pct": 35.172413793103445
      },
      {
        "date": "2026-01-06",
        "win_pct": 35.374149659863946
      },
      {
        "date": "2026-01-07",
        "win_pct": 35.57046979865772
      },
      {
        "date": "2026-01-08",
        "win_pct": 35.526315789473685
      },
      {
        "date": "2026-01-09",
        "win_pct": 35.947712418300654
      },
      {
        "date": "2026-01-10",
        "win_pct": 36.53846153846153
      },
      {
        "date": "2026-01-11",
        "win_pct": 36.30573248407643
      },
      {
        "date": "2026-01-12",
        "win_pct": 36.875
      },
      {
        "date": "2026-01-13",
        "win_pct": 37.267080745341616
      },
      {
        "date": "2026-01-14",
        "win_pct": 36.809815950920246
      },
      {
        "date": "2026-01-15",
        "win_pct": 37.95180722891566
      },
      {
        "date": "2026-01-16",
        "win_pct": 38.32335329341318
      },
      {
        "date": "2026-01-17",
        "win_pct": 38.59649122807017
      },
      {
        "date": "2026-01-18",
        "win_pct": 38.95348837209303
      },
      {
        "date": "2026-01-19",
        "win_pct": 39.42857142857143
      },
      {
        "date": "2026-01-20",
        "win_pct": 39.20454545454545
      },
      {
        "date": "2026-01-21",
        "win_pct": 38.764044943820224
      },
      {
        "date": "2026-01-22",
        "win_pct": 39.226519337016576
      }
    ],
    "Adam": [
      {
        "date": "2025-10-21",
        "win_pct": 0
      },
      {
        "date": "2025-10-22",
        "win_pct": 0.0
      },
      {
        "date": "2025-10-23",
        "win_pct": 0.0
      },
      {
        "date": "2025-10-24",
        "win_pct": 28.57142857142857
      },
      {
        "date": "2025-10-25",
        "win_pct": 37.5
      },
      {
        "date": "2025-10-26",
        "win_pct": 36.36363636363637
      },
      {
        "date": "2025-10-27",
        "win_pct": 46.15384615384615
      },
      {
        "date": "2025-10-28",
        "win_pct": 46.666666666666664
      },
      {
        "date": "2025-10-29",
        "win_pct": 50.0
      },
      {
        "date": "2025-10-30",
        "win_pct": 47.368421052631575
      },
      {
        "date": "2025-10-31",
        "win_pct": 47.61904761904761
      },
      {
        "date": "2025-11-01",
        "win_pct": 47.82608695652174
      },
      {
        "date": "2025-11-02",
        "win_pct": 45.83333333333333
      },
      {
        "date": "2025-11-03",
        "win_pct": 46.42857142857143
      },
      {
        "date": "2025-11-04",
        "win_pct": 46.42857142857143
      },
      {
        "date": "2025-11-05",
        "win_pct": 50.0
      },
      {
        "date": "2025-11-06",
        "win_pct": 50.0
      },
      {
        "date": "2025-11-07",
        "win_pct": 50.0
      },
      {
        "date": "2025-11-08",
        "win_pct": 52.63157894736842
      },
      {
        "date": "2025-11-09",
        "win_pct": 52.5
      },
      {
        "date": "2025-11-10",
        "win_pct": 53.65853658536586
      },
      {
        "date": "2025-11-11",
        "win_pct": 52.27272727272727
      },
      {
        "date": "2025-11-12",
        "win_pct": 52.083333333333336
      },
      {
        "date": "2025-11-13",
        "win_pct": 52.083333333333336
      },
      {
        "date": "2025-11-14",
        "win_pct": 50.0
      },
      {
        "date": "2025-11-15",
        "win_pct": 50.98039215686274
      },
      {
        "date": "2025-11-16",
        "win_pct": 50.943396226415096
      },
      {
        "date": "2025-11-17",
        "win_pct": 50.90909090909091
      },
      {
        "date": "2025-11-18",
        "win_pct": 51.78571428571429
      },
      {
        "date": "2025-11-19",
        "win_pct": 52.54237288135594
      },
      {
        "date": "2025-11-20",
        "win_pct": 51.66666666666667
      },
      {
        "date": "2025-11-21",
        "win_pct": 52.38095238095239
      },
      {
        "date": "2025-11-22",
        "win_pct": 52.307692307692314
      },
      {
        "date": "2025-11-23",
        "win_pct": 53.73134328358209
      },
      {
        "date": "2025-11-24",
        "win_pct": 55.714285714285715
      },
      {
        "date": "2025-11-25",
        "win_pct": 55.714285714285715
      },
      {
        "date": "2025-11-26",
        "win_pct": 56.16438356164384
      },
      {
        "date": "2025-11-28",
        "win_pct": 54.666666666666664
      },
      {
        "date": "2025-11-29",
        "win_pct": 53.84615384615385
      },
      {
        "date": "2025-11-30",
        "win_pct": 53.75
      },
      {
        "date": "2025-12-01",
        "win_pct": 53.65853658536586
      },
      {
        "date": "2025-12-02",
        "win_pct": 54.21686746987952
      },
      {
        "date": "2025-12-03",
        "win_pct": 53.48837209302325
      },
      {
        "date": "2025-12-04",
        "win_pct": 54.02298850574713
      },
      {
        "date": "2025-12-05",
        "win_pct": 54.44444444444444
      },
      {
        "date": "2025-12-06",
        "win_pct": 54.347826086956516
      },
      {
        "date": "2025-12-07",
        "win_pct": 55.319148936170215
      },
      {
        "date": "2025-12-08",
        "win_pct": 54.736842105263165
      },
      {
        "date": "2025-12-09",
        "win_pct": 54.166666666666664
      },
      {
        "date": "2025-12-10",
        "win_pct": 54.166666666666664
      },
      {
        "date": "2025-12-11",
        "win_pct": 53.535353535353536
      },
      {
        "date": "2025-12-12",
        "win_pct": 53.535353535353536
      },
      {
        "date": "2025-12-13",
        "win_pct": 53.535353535353536
      },
      {
        "date": "2025-12-14",
        "win_pct": 53.0
      },
      {
        "date": "2025-12-15",
        "win_pct": 52.42718446601942
      },
      {
        "date": "2025-12-17",
        "win_pct": 52.42718446601942
      },
      {
        "date": "2025-12-18",
        "win_pct": 52.83018867924528
      },
      {
        "date": "2025-12-19",
        "win_pct": 52.77777777777778
      },
      {
        "date": "2025-12-20",
        "win_pct": 52.25225225225225
      },
      {
        "date": "2025-12-21",
        "win_pct": 52.21238938053098
      },
      {
        "date": "2025-12-22",
        "win_pct": 53.04347826086957
      },
      {
        "date": "2025-12-23",
        "win_pct": 51.69491525423729
      },
      {
        "date": "2025-12-25",
        "win_pct": 52.10084033613446
      },
      {
        "date": "2025-12-26",
        "win_pct": 52.892561983471076
      },
      {
        "date": "2025-12-27",
        "win_pct": 53.2258064516129
      },
      {
        "date": "2025-12-28",
        "win_pct": 52.38095238095239
      },
      {
        "date": "2025-12-29",
        "win_pct": 52.34375
      },
      {
        "date": "2025-12-30",
        "win_pct": 52.307692307692314
      },
      {
        "date": "2025-12-31",
        "win_pct": 52.67175572519084
      },
      {
        "date": "2026-01-01",
        "win_pct": 52.98507462686567
      },
      {
        "date": "2026-01-02",
        "win_pct": 52.20588235294118
      },
      {
        "date": "2026-01-03",
        "win_pct": 52.17391304347826
      },
      {
        "date": "2026-01-04",
        "win_pct": 51.77304964539007
      },
      {
        "date": "2026-01-05",
        "win_pct": 52.44755244755245
      },
      {
        "date": "2026-01-06",
        "win_pct": 51.724137931034484
      },
      {
        "date": "2026-01-07",
        "win_pct": 51.70068027210885
      },
      {
        "date": "2026-01-08",
        "win_pct": 51.70068027210885
      },
      {
        "date": "2026-01-09",
        "win_pct": 51.33333333333333
      },
      {
        "date": "2026-01-10",
        "win_pct": 50.6578947368421
      },
      {
        "date": "2026-01-11",
        "win_pct": 50.967741935483865
      },
      {
        "date": "2026-01-12",
        "win_pct": 50.955414012738856
      },
      {
        "date": "2026-01-13",
        "win_pct": 51.57232704402516
      },
      {
        "date": "2026-01-14",
        "win_pct": 52.17391304347826
      },
      {
        "date": "2026-01-15",
        "win_pct": 52.14723926380368
      },
      {
        "date": "2026-01-16",
        "win_pct": 52.4390243902439
      },
      {
        "date": "2026-01-17",
        "win_pct": 53.293413173652695
      },
      {
        "date": "2026-01-18",
        "win_pct": 52.662721893491124
      },
      {
        "date": "2026-01-19",
        "win_pct": 52.046783625730995
      },
      {
        "date": "2026-01-20",
        "win_pct": 51.724137931034484
      },
      {
        "date": "2026-01-21",
        "win_pct": 51.70454545454546
      },
      {
        "date": "2026-01-22",
        "win_pct": 51.68539325842697
      }
    ],
    "Duke": [
      {
        "date": "2025-10-21",
        "win_pct": 0
      },
      {
        "date": "2025-10-22",
        "win_pct": 75.0
      },
      {
        "date": "2025-10-23",
        "win_pct": 75.0
      },
      {
        "date": "2025-10-24",
        "win_pct": 71.42857142857143
      },
      {
        "date": "2025-10-25",
        "win_pct": 75.0
      },
      {
        "date": "2025-10-26",
        "win_pct": 63.63636363636363
      },
      {
        "date": "2025-10-27",
        "win_pct": 61.53846153846154
      },
      {
        "date": "2025-10-28",
        "win_pct": 53.333333333333336
      },
      {
        "date": "2025-10-29",
        "win_pct": 52.94117647058824
      },
      {
        "date": "2025-10-30",
        "win_pct": 52.94117647058824
      },
      {
        "date": "2025-10-31",
        "win_pct": 57.14285714285714
      },
      {
        "date": "2025-11-01",
        "win_pct": 57.14285714285714
      },
      {
        "date": "2025-11-02",
        "win_pct": 58.333333333333336
      },
      {
        "date": "2025-11-03",
        "win_pct": 57.692307692307686
      },
      {
        "date": "2025-11-04",
        "win_pct": 58.620689655172406
      },
      {
        "date": "2025-11-05",
        "win_pct": 60.0
      },
      {
        "date": "2025-11-06",
        "win_pct": 58.06451612903226
      },
      {
        "date": "2025-11-07",
        "win_pct": 57.57575757575758
      },
      {
        "date": "2025-11-08",
        "win_pct": 52.77777777777778
      },
      {
        "date": "2025-11-09",
        "win_pct": 54.054054054054056
      },
      {
        "date": "2025-11-10",
        "win_pct": 51.28205128205128
      },
      {
        "date": "2025-11-11",
        "win_pct": 53.65853658536586
      },
      {
        "date": "2025-11-12",
        "win_pct": 50.0
      },
      {
        "date": "2025-11-13",
        "win_pct": 51.11111111111111
      },
      {
        "date": "2025-11-14",
        "win_pct": 53.191489361702125
      },
      {
        "date": "2025-11-15",
        "win_pct": 54.166666666666664
      },
      {
        "date": "2025-11-16",
        "win_pct": 52.0
      },
      {
        "date": "2025-11-17",
        "win_pct": 51.85185185185185
      },
      {
        "date": "2025-11-18",
        "win_pct": 51.85185185185185
      },
      {
        "date": "2025-11-19",
        "win_pct": 54.385964912280706
      },
      {
        "date": "2025-11-20",
        "win_pct": 53.44827586206896
      },
      {
        "date": "2025-11-21",
        "win_pct": 53.333333333333336
      },
      {
        "date": "2025-11-22",
        "win_pct": 53.96825396825397
      },
      {
        "date": "2025-11-23",
        "win_pct": 53.84615384615385
      },
      {
        "date": "2025-11-24",
        "win_pct": 54.41176470588235
      },
      {
        "date": "2025-11-25",
        "win_pct": 53.62318840579711
      },
      {
        "date": "2025-11-26",
        "win_pct": 54.929577464788736
      },
      {
        "date": "2025-11-28",
        "win_pct": 54.054054054054056
      },
      {
        "date": "2025-11-29",
        "win_pct": 51.94805194805194
      },
      {
        "date": "2025-11-30",
        "win_pct": 51.89873417721519
      },
      {
        "date": "2025-12-01",
        "win_pct": 50.617283950617285
      },
      {
        "date": "2025-12-02",
        "win_pct": 50.602409638554214
      },
      {
        "date": "2025-12-03",
        "win_pct": 51.162790697674424
      },
      {
        "date": "2025-12-04",
        "win_pct": 50.57471264367817
      },
      {
        "date": "2025-12-05",
        "win_pct": 49.45054945054945
      },
      {
        "date": "2025-12-06",
        "win_pct": 48.91304347826087
      },
      {
        "date": "2025-12-07",
        "win_pct": 48.421052631578945
      },
      {
        "date": "2025-12-08",
        "win_pct": 48.421052631578945
      },
      {
        "date": "2025-12-09",
        "win_pct": 48.45360824742268
      },
      {
        "date": "2025-12-10",
        "win_pct": 48.45360824742268
      },
      {
        "date": "2025-12-11",
        "win_pct": 47.95918367346938
      },
      {
        "date": "2025-12-12",
        "win_pct": 48.484848484848484
      },
      {
        "date": "2025-12-13",
        "win_pct": 49.0
      },
      {
        "date": "2025-12-14",
        "win_pct": 48.51485148514851
      },
      {
        "date": "2025-12-15",
        "win_pct": 48.54368932038835
      },
      {
        "date": "2025-12-17",
        "win_pct": 49.03846153846153
      },
      {
        "date": "2025-12-18",
        "win_pct": 49.532710280373834
      },
      {
        "date": "2025-12-19",
        "win_pct": 49.54128440366973
      },
      {
        "date": "2025-12-20",
        "win_pct": 49.549549549549546
      },
      {
        "date": "2025-12-21",
        "win_pct": 50.0
      },
      {
        "date": "2025-12-22",
        "win_pct": 50.0
      },
      {
        "date": "2025-12-23",
        "win_pct": 50.847457627118644
      },
      {
        "date": "2025-12-25",
        "win_pct": 51.26050420168067
      },
      {
        "date": "2025-12-26",
        "win_pct": 51.63934426229508
      },
      {
        "date": "2025-12-27",
        "win_pct": 51.61290322580645
      },
      {
        "date": "2025-12-28",
        "win_pct": 52.38095238095239
      },
      {
        "date": "2025-12-29",
        "win_pct": 52.71317829457365
      },
      {
        "date": "2025-12-30",
        "win_pct": 53.07692307692308
      },
      {
        "date": "2025-12-31",
        "win_pct": 52.63157894736842
      },
      {
        "date": "2026-01-01",
        "win_pct": 52.98507462686567
      },
      {
        "date": "2026-01-02",
        "win_pct": 52.94117647058824
      },
      {
        "date": "2026-01-03",
        "win_pct": 52.142857142857146
      },
      {
        "date": "2026-01-04",
        "win_pct": 52.142857142857146
      },
      {
        "date": "2026-01-05",
        "win_pct": 52.083333333333336
      },
      {
        "date": "2026-01-06",
        "win_pct": 52.083333333333336
      },
      {
        "date": "2026-01-07",
        "win_pct": 52.02702702702703
      },
      {
        "date": "2026-01-08",
        "win_pct": 52.02702702702703
      },
      {
        "date": "2026-01-09",
        "win_pct": 51.65562913907284
      },
      {
        "date": "2026-01-10",
        "win_pct": 52.28758169934641
      },
      {
        "date": "2026-01-11",
        "win_pct": 52.903225806451616
      },
      {
        "date": "2026-01-12",
        "win_pct": 52.86624203821656
      },
      {
        "date": "2026-01-13",
        "win_pct": 52.53164556962025
      },
      {
        "date": "2026-01-14",
        "win_pct": 53.086419753086425
      },
      {
        "date": "2026-01-15",
        "win_pct": 52.760736196319016
      },
      {
        "date": "2026-01-16",
        "win_pct": 52.40963855421686
      },
      {
        "date": "2026-01-17",
        "win_pct": 52.09580838323353
      },
      {
        "date": "2026-01-18",
        "win_pct": 52.071005917159766
      },
      {
        "date": "2026-01-19",
        "win_pct": 52.046783625730995
      },
      {
        "date": "2026-01-20",
        "win_pct": 52.29885057471264
      },
      {
        "date": "2026-01-21",
        "win_pct": 52.84090909090909
      },
      {
        "date": "2026-01-22",
        "win_pct": 53.37078651685393
      }
    ],
    "Nick": [
      {
        "date": "2025-10-21",
        "win_pct": 0.0
      },
      {
        "date": "2025-10-22",
        "win_pct": 50.0
      },
      {
        "date": "2025-10-23",
        "win_pct": 50.0
      },
      {
        "date": "2025-10-24",
        "win_pct": 42.857142857142854
      },
      {
        "date": "2025-10-25",
        "win_pct": 50.0
      },
      {
        "date": "2025-10-26",
        "win_pct": 50.0
      },
      {
        "date": "2025-10-27",
        "win_pct": 57.14285714285714
      },
      {
        "date": "2025-10-28",
        "win_pct": 60.0
      },
      {
        "date": "2025-10-29",
        "win_pct": 61.111111111111114
      },
      {
        "date": "2025-10-30",
        "win_pct": 61.111111111111114
      },
      {
        "date": "2025-10-31",
        "win_pct": 60.0
      },
      {
        "date": "2025-11-01",
        "win_pct": 63.63636363636363
      },
      {
        "date": "2025-11-02",
        "win_pct": 65.21739130434783
      },
      {
        "date": "2025-11-03",
        "win_pct": 65.38461538461539
      },
      {
        "date": "2025-11-04",
        "win_pct": 62.96296296296296
      },
      {
        "date": "2025-11-05",
        "win_pct": 61.29032258064516
      },
      {
        "date": "2025-11-06",
        "win_pct": 61.29032258064516
      },
      {
        "date": "2025-11-07",
        "win_pct": 60.60606060606061
      },
      {
        "date": "2025-11-08",
        "win_pct": 60.0
      },
      {
        "date": "2025-11-09",
        "win_pct": 60.526315789473685
      },
      {
        "date": "2025-11-10",
        "win_pct": 60.0
      },
      {
        "date": "2025-11-11",
        "win_pct": 60.97560975609756
      },
      {
        "date": "2025-11-12",
        "win_pct": 62.7906976744186
      },
      {
        "date": "2025-11-13",
        "win_pct": 62.7906976744186
      },
      {
        "date": "2025-11-14",
        "win_pct": 61.702127659574465
      },
      {
        "date": "2025-11-15",
        "win_pct": 60.416666666666664
      },
      {
        "date": "2025-11-16",
        "win_pct": 60.0
      },
      {
        "date": "2025-11-17",
        "win_pct": 61.53846153846154
      },
      {
        "date": "2025-11-18",
        "win_pct": 60.37735849056604
      },
      {
        "date": "2025-11-19",
        "win_pct": 59.64912280701754
      },
      {
        "date": "2025-11-20",
        "win_pct": 60.3448275862069
      },
      {
        "date": "2025-11-21",
        "win_pct": 59.01639344262295
      },
      {
        "date": "2025-11-22",
        "win_pct": 59.01639344262295
      },
      {
        "date": "2025-11-23",
        "win_pct": 57.14285714285714
      },
      {
        "date": "2025-11-24",
        "win_pct": 57.57575757575758
      },
      {
        "date": "2025-11-25",
        "win_pct": 56.71641791044776
      },
      {
        "date": "2025-11-26",
        "win_pct": 55.714285714285715
      },
      {
        "date": "2025-11-28",
        "win_pct": 56.33802816901409
      },
      {
        "date": "2025-11-29",
        "win_pct": 56.94444444444444
      },
      {
        "date": "2025-11-30",
        "win_pct": 56.57894736842105
      },
      {
        "date": "2025-12-01",
        "win_pct": 55.84415584415584
      },
      {
        "date": "2025-12-02",
        "win_pct": 56.25
      },
      {
        "date": "2025-12-03",
        "win_pct": 57.3170731707317
      },
      {
        "date": "2025-12-04",
        "win_pct": 58.333333333333336
      },
      {
        "date": "2025-12-05",
        "win_pct": 58.620689655172406
      },
      {
        "date": "2025-12-06",
        "win_pct": 58.42696629213483
      },
      {
        "date": "2025-12-07",
        "win_pct": 57.14285714285714
      },
      {
        "date": "2025-12-08",
        "win_pct": 56.52173913043478
      },
      {
        "date": "2025-12-09",
        "win_pct": 56.52173913043478
      },
      {
        "date": "2025-12-10",
        "win_pct": 56.52173913043478
      },
      {
        "date": "2025-12-11",
        "win_pct": 56.38297872340425
      },
      {
        "date": "2025-12-12",
        "win_pct": 57.291666666666664
      },
      {
        "date": "2025-12-13",
        "win_pct": 57.291666666666664
      },
      {
        "date": "2025-12-14",
        "win_pct": 57.57575757575758
      },
      {
        "date": "2025-12-15",
        "win_pct": 56.99999999999999
      },
      {
        "date": "2025-12-17",
        "win_pct": 56.43564356435643
      },
      {
        "date": "2025-12-18",
        "win_pct": 56.310679611650485
      },
      {
        "date": "2025-12-19",
        "win_pct": 57.14285714285714
      },
      {
        "date": "2025-12-20",
        "win_pct": 58.333333333333336
      },
      {
        "date": "2025-12-21",
        "win_pct": 58.18181818181818
      },
      {
        "date": "2025-12-22",
        "win_pct": 57.65765765765766
      },
      {
        "date": "2025-12-23",
        "win_pct": 56.52173913043478
      },
      {
        "date": "2025-12-25",
        "win_pct": 56.41025641025641
      },
      {
        "date": "2025-12-26",
        "win_pct": 55.46218487394958
      },
      {
        "date": "2025-12-27",
        "win_pct": 55.371900826446286
      },
      {
        "date": "2025-12-28",
        "win_pct": 55.28455284552846
      },
      {
        "date": "2025-12-29",
        "win_pct": 56.34920634920635
      },
      {
        "date": "2025-12-30",
        "win_pct": 56.69291338582677
      },
      {
        "date": "2025-12-31",
        "win_pct": 55.81395348837209
      },
      {
        "date": "2026-01-01",
        "win_pct": 56.48854961832062
      },
      {
        "date": "2026-01-02",
        "win_pct": 56.81818181818182
      },
      {
        "date": "2026-01-03",
        "win_pct": 57.35294117647059
      },
      {
        "date": "2026-01-04",
        "win_pct": 57.66423357664233
      },
      {
        "date": "2026-01-05",
        "win_pct": 57.85714285714286
      },
      {
        "date": "2026-01-06",
        "win_pct": 58.156028368794324
      },
      {
        "date": "2026-01-07",
        "win_pct": 58.333333333333336
      },
      {
        "date": "2026-01-08",
        "win_pct": 58.620689655172406
      },
      {
        "date": "2026-01-09",
        "win_pct": 58.78378378378378
      },
      {
        "date": "2026-01-10",
        "win_pct": 58.38926174496645
      },
      {
        "date": "2026-01-11",
        "win_pct": 57.51633986928104
      },
      {
        "date": "2026-01-12",
        "win_pct": 57.7922077922078
      },
      {
        "date": "2026-01-13",
        "win_pct": 57.961783439490446
      },
      {
        "date": "2026-01-14",
        "win_pct": 57.59493670886076
      },
      {
        "date": "2026-01-15",
        "win_pct": 57.49999999999999
      },
      {
        "date": "2026-01-16",
        "win_pct": 57.05521472392638
      },
      {
        "date": "2026-01-17",
        "win_pct": 56.96969696969697
      },
      {
        "date": "2026-01-18",
        "win_pct": 57.48502994011976
      },
      {
        "date": "2026-01-19",
        "win_pct": 57.738095238095234
      },
      {
        "date": "2026-01-20",
        "win_pct": 57.30994152046783
      },
      {
        "date": "2026-01-21",
        "win_pct": 57.30994152046783
      },
      {
        "date": "2026-01-22",
        "win_pct": 57.14285714285714
      }
    ],
    "Undrafted": [
      {
        "date": "2025-10-21",
        "win_pct": 0
      },
      {
        "date": "2025-10-22",
        "win_pct": 50.0
      },
      {
        "date": "2025-10-23",
        "win_pct": 50.0
      },
      {
        "date": "2025-10-24",
        "win_pct": 25.0
      },
      {
        "date": "2025-10-25",
        "win_pct": 25.0
      },
      {
        "date": "2025-10-26",
        "win_pct": 20.0
      },
      {
        "date": "2025-10-27",
        "win_pct": 28.57142857142857
      },
      {
        "date": "2025-10-28",
        "win_pct": 28.57142857142857
      },
      {
        "date": "2025-10-29",
        "win_pct": 22.22222222222222
      },
      {
        "date": "2025-10-30",
        "win_pct": 22.22222222222222
      },
      {
        "date": "2025-10-31",
        "win_pct": 20.0
      },
      {
        "date": "2025-11-01",
        "win_pct": 20.0
      },
      {
        "date": "2025-11-02",
        "win_pct": 16.666666666666664
      },
      {
        "date": "2025-11-03",
        "win_pct": 21.428571428571427
      },
      {
        "date": "2025-11-04",
        "win_pct": 21.428571428571427
      },
      {
        "date": "2025-11-05",
        "win_pct": 25.0
      },
      {
        "date": "2025-11-06",
        "win_pct": 25.0
      },
      {
        "date": "2025-11-07",
        "win_pct": 22.22222222222222
      },
      {
        "date": "2025-11-08",
        "win_pct": 22.22222222222222
      },
      {
        "date": "2025-11-09",
        "win_pct": 21.052631578947366
      },
      {
        "date": "2025-11-10",
        "win_pct": 20.0
      },
      {
        "date": "2025-11-11",
        "win_pct": 22.727272727272727
      },
      {
        "date": "2025-11-12",
        "win_pct": 22.727272727272727
      },
      {
        "date": "2025-11-13",
        "win_pct": 21.73913043478261
      },
      {
        "date": "2025-11-14",
        "win_pct": 20.833333333333336
      },
      {
        "date": "2025-11-15",
        "win_pct": 20.833333333333336
      },
      {
        "date": "2025-11-16",
        "win_pct": 26.923076923076923
      },
      {
        "date": "2025-11-17",
        "win_pct": 26.923076923076923
      },
      {
        "date": "2025-11-18",
        "win_pct": 25.0
      },
      {
        "date": "2025-11-19",
        "win_pct": 25.0
      },
      {
        "date": "2025-11-20",
        "win_pct": 25.0
      },
      {
        "date": "2025-11-21",
        "win_pct": 26.666666666666668
      },
      {
        "date": "2025-11-22",
        "win_pct": 26.666666666666668
      },
      {
        "date": "2025-11-23",
        "win_pct": 25.0
      },
      {
        "date": "2025-11-24",
        "win_pct": 23.52941176470588
      },
      {
        "date": "2025-11-25",
        "win_pct": 23.52941176470588
      },
      {
        "date": "2025-11-26",
        "win_pct": 23.52941176470588
      },
      {
        "date": "2025-11-28",
        "win_pct": 25.0
      },
      {
        "date": "2025-11-29",
        "win_pct": 24.324324324324326
      },
      {
        "date": "2025-11-30",
        "win_pct": 23.684210526315788
      },
      {
        "date": "2025-12-01",
        "win_pct": 27.500000000000004
      },
      {
        "date": "2025-12-02",
        "win_pct": 27.500000000000004
      },
      {
        "date": "2025-12-03",
        "win_pct": 29.268292682926827
      },
      {
        "date": "2025-12-04",
        "win_pct": 30.23255813953488
      },
      {
        "date": "2025-12-05",
        "win_pct": 29.545454545454547
      },
      {
        "date": "2025-12-06",
        "win_pct": 31.11111111111111
      },
      {
        "date": "2025-12-07",
        "win_pct": 30.434782608695656
      },
      {
        "date": "2025-12-08",
        "win_pct": 30.434782608695656
      },
      {
        "date": "2025-12-09",
        "win_pct": 30.434782608695656
      },
      {
        "date": "2025-12-10",
        "win_pct": 30.434782608695656
      },
      {
        "date": "2025-12-11",
        "win_pct": 30.434782608695656
      },
      {
        "date": "2025-12-12",
        "win_pct": 31.25
      },
      {
        "date": "2025-12-13",
        "win_pct": 31.25
      },
      {
        "date": "2025-12-14",
        "win_pct": 32.6530612244898
      },
      {
        "date": "2025-12-15",
        "win_pct": 34.0
      },
      {
        "date": "2025-12-17",
        "win_pct": 34.0
      },
      {
        "date": "2025-12-18",
        "win_pct": 32.69230769230769
      },
      {
        "date": "2025-12-19",
        "win_pct": 32.69230769230769
      },
      {
        "date": "2025-12-20",
        "win_pct": 32.075471698113205
      },
      {
        "date": "2025-12-21",
        "win_pct": 33.33333333333333
      },
      {
        "date": "2025-12-22",
        "win_pct": 32.72727272727273
      },
      {
        "date": "2025-12-23",
        "win_pct": 33.33333333333333
      },
      {
        "date": "2025-12-25",
        "win_pct": 33.33333333333333
      },
      {
        "date": "2025-12-26",
        "win_pct": 34.48275862068966
      },
      {
        "date": "2025-12-27",
        "win_pct": 36.666666666666664
      },
      {
        "date": "2025-12-28",
        "win_pct": 36.666666666666664
      },
      {
        "date": "2025-12-29",
        "win_pct": 36.0655737704918
      },
      {
        "date": "2025-12-30",
        "win_pct": 35.483870967741936
      },
      {
        "date": "2025-12-31",
        "win_pct": 35.483870967741936
      },
      {
        "date": "2026-01-01",
        "win_pct": 34.375
      },
      {
        "date": "2026-01-02",
        "win_pct": 33.84615384615385
      },
      {
        "date": "2026-01-03",
        "win_pct": 33.33333333333333
      },
      {
        "date": "2026-01-04",
        "win_pct": 34.32835820895522
      },
      {
        "date": "2026-01-05",
        "win_pct": 33.82352941176471
      },
      {
        "date": "2026-01-06",
        "win_pct": 33.82352941176471
      },
      {
        "date": "2026-01-07",
        "win_pct": 32.857142857142854
      },
      {
        "date": "2026-01-08",
        "win_pct": 33.80281690140845
      },
      {
        "date": "2026-01-09",
        "win_pct": 33.33333333333333
      },
      {
        "date": "2026-01-10",
        "win_pct": 32.87671232876712
      },
      {
        "date": "2026-01-11",
        "win_pct": 32.432432432432435
      },
      {
        "date": "2026-01-12",
        "win_pct": 32.89473684210527
      },
      {
        "date": "2026-01-13",
        "win_pct": 32.89473684210527
      },
      {
        "date": "2026-01-14",
        "win_pct": 32.05128205128205
      },
      {
        "date": "2026-01-15",
        "win_pct": 31.645569620253166
      },
      {
        "date": "2026-01-16",
        "win_pct": 32.5
      },
      {
        "date": "2026-01-17",
        "win_pct": 32.098765432098766
      },
      {
        "date": "2026-01-18",
        "win_pct": 31.70731707317073
      },
      {
        "date": "2026-01-19",
        "win_pct": 30.952380952380953
      },
      {
        "date": "2026-01-20",
        "win_pct": 31.76470588235294
      },
      {
        "date": "2026-01-21",
        "win_pct": 31.3953488372093
      },
      {
        "date": "2026-01-22",
        "win_pct": 31.03448275862069
      }
    ]
  },
  "todays_games": [
    {
      "visitor": "Houston Rockets",
      "home": "Detroit Pistons",
      "time": "7:00 pm ET",
      "visitor_friend": "Nick",
      "home_friend": "JJ"
    },
    {
      "visitor": "Phoenix Suns",
      "home": "Atlanta Hawks",
      "time": "7:30 pm ET",
      "visitor_friend": "Nate",
      "home_friend": "Nate"
    },
    {
      "visitor": "Boston Celtics",
      "home": "Brooklyn Nets",
      "time": "7:30 pm ET",
      "visitor_friend": "Adam",
      "home_friend": "Undrafted"
    },
    {
      "visitor": "Sacramento Kings",
      "home": "Cleveland Cavaliers",
      "time": "7:30 pm ET",
      "visitor_friend": "Adam",
      "home_friend": "Andy"
    },
    {
      "visitor": "New Orleans Pelicans",
      "home": "Memphis Grizzlies",
      "time": "8:00 pm ET",
      "visitor_friend": "JJ",
      "home_friend": "Nate"
    },
    {
      "visitor": "Indiana Pacers",
      "home": "Oklahoma City Thunder",
      "time": "8:00 pm ET",
      "visitor_friend": "Chris",
      "home_friend": "JJ"
    },
    {
      "visitor": "Denver Nuggets",
      "home": "Milwaukee Bucks",
      "time": "9:30 pm ET",
      "visitor_friend": "Adam",
      "home_friend": "Andy"
    },
    {
      "visitor": "Toronto Raptors",
      "home": "Portland Trail Blazers",
      "time": "10:00 pm ET",
      "visitor_friend": "Duke",
      "home_friend": "Nick"
    }
  ],
  "yesterdays_games": [
    {
      "visitor": "Denver Nuggets",
      "home": "Washington Wizards",
      "visitor_score": 107,
      "home_score": 97,
      "visitor_friend": "Adam",
      "home_friend": "Andy"
    },
    {
      "visitor": "Charlotte Hornets",
      "home": "Orlando Magic",
      "visitor_score": 124,
      "home_score": 97,
      "visitor_friend": "Chris",
      "home_friend": "Nate"
    },
    {
      "visitor": "Houston Rockets",
      "home": "Philadelphia 76ers",
      "visitor_score": 122,
      "home_score": 128,
      "visitor_friend": "Nick",
      "home_friend": "Nick"
    },
    {
      "visitor": "Chicago Bulls",
      "home": "Minnesota Timberwolves",
      "visitor_score": 120,
      "home_score": 115,
      "visitor_friend": "Duke",
      "home_friend": "Nick"
    },
    {
      "visitor": "Golden State Warriors",
      "home": "Dallas Mavericks",
      "visitor_score": 115,
      "home_score": 123,
      "visitor_friend": "Chris",
      "home_friend": "Chris"
    },
    {
      "visitor": "San Antonio Spurs",
      "home": "Utah Jazz",
      "visitor_score": 126,
      "home_score": 109,
      "visitor_friend": "JJ",
      "home_friend": "Undrafted"
    },
    {
      "visitor": "Miami Heat",
      "home": "Portland Trail Blazers",
      "visitor_score": 110,
      "home_score": 127,
      "visitor_friend": "Adam",
      "home_friend": "Nick"
    },
    {
      "visitor": "Los Angeles Lakers",
      "home": "LA Clippers",
      "visitor_score": 104,
      "home_score": 112,
      "visitor_friend": "Andy",
      "home_friend": "Duke"
    }
  ]
}